{
    "id": "LUCENE-5834",
    "title": "Make empty doc values impls singletons",
    "details": {
        "type": "Improvement",
        "priority": "Trivial",
        "labels": "",
        "resolution": "Fixed",
        "components": [],
        "affect_versions": "None",
        "status": "Resolved",
        "fix_versions": [
            "4.10",
            "6.0"
        ]
    },
    "description": "Making these empty instances singletons would allow to use unwrapSingleton to check if they are single-valued.",
    "attachments": {
        "LUCENE-5834.patch": "https://issues.apache.org/jira/secure/attachment/12656720/LUCENE-5834.patch"
    },
    "issue_links": {},
    "comments": [
        {
            "id": "comment-14067480",
            "author": "Adrien Grand",
            "content": "Patch. ",
            "date": "2014-07-19T10:45:34+0000"
        },
        {
            "id": "comment-14067510",
            "author": "Robert Muir",
            "content": "+1 ",
            "date": "2014-07-19T12:54:41+0000"
        },
        {
            "id": "comment-14068424",
            "author": "ASF subversion and git services",
            "content": "Commit 1612251 from Adrien Grand in branch 'dev/trunk'\n[ https://svn.apache.org/r1612251 ]\n\nLUCENE-5834: Empty sorted set and numeric doc values are now singletons. ",
            "date": "2014-07-21T11:31:11+0000"
        },
        {
            "id": "comment-14068425",
            "author": "ASF subversion and git services",
            "content": "Commit 1612252 from Adrien Grand in branch 'dev/branches/branch_4x'\n[ https://svn.apache.org/r1612252 ]\n\nLUCENE-5834: Empty sorted set and numeric doc values are now singletons. ",
            "date": "2014-07-21T11:33:11+0000"
        }
    ]
}