{
    "id": "LUCENE-3877",
    "title": "Lucene should not call System.out.println",
    "details": {
        "labels": "",
        "priority": "Major",
        "components": [],
        "type": "Bug",
        "fix_versions": [
            "4.0-ALPHA",
            "6.0"
        ],
        "affect_versions": "None",
        "resolution": "Fixed",
        "status": "Closed"
    },
    "description": "We seem to have accumulated a few random sops...\n\nEg, PairOutputs.java (oal.util.fst) and MultiDocValues.java, at least.\n\nCan we somehow detect (eg, have a test failure) if we accidentally leave errant System.out.println's (leftover from debugging)...?",
    "attachments": {
        "SystemPrintCheck.java": "https://issues.apache.org/jira/secure/attachment/12519322/SystemPrintCheck.java",
        "IllegalSystemTest.java": "https://issues.apache.org/jira/secure/attachment/12519206/IllegalSystemTest.java",
        "LUCENE-3877.patch": "https://issues.apache.org/jira/secure/attachment/12535811/LUCENE-3877.patch"
    },
    "issue_links": {},
    "comments": [
        {
            "date": "2012-03-16T10:56:24+0000",
            "content": "Lots of tests write to std streams currently (solr). We could do that fairly easily (in a number of ways) but it'll break a number of tests. ",
            "author": "Dawid Weiss",
            "id": "comment-13231053"
        },
        {
            "date": "2012-03-16T11:56:21+0000",
            "content": "I think it's fine if tests write to the std streams, but not core Lucene code (lucene/core/src/java/*)? ",
            "author": "Michael McCandless",
            "id": "comment-13231090"
        },
        {
            "date": "2012-03-16T12:07:29+0000",
            "content": "This is possible by verifying where System.out takes place at runtime via stack analysis. Alternatively a bytecode woven aspect. But at the same time it could also be a find-and-grep over sources? Comments would have to be removed in the pipeline prior to grepping for sysouts.\n\nChecking all sysouts/syserrs and verifying stack traces there seems like an overkill compared to the above. ",
            "author": "Dawid Weiss",
            "id": "comment-13231095"
        },
        {
            "date": "2012-03-16T12:09:41+0000",
            "content": "findbugs? checkstyle? ",
            "author": "Benson Margulies",
            "id": "comment-13231098"
        },
        {
            "date": "2012-03-16T13:43:58+0000",
            "content": "Don't we now fail if there is a noncommit in the src? Can't we use the same mechanism? ",
            "author": "Mark Miller",
            "id": "comment-13231176"
        },
        {
            "date": "2012-03-16T14:57:12+0000",
            "content": "Some core code legitimately uses System.out.println, e.g. CheckIndex.\n\nHowever on review, some of its use cases should actually be System.err... ",
            "author": "Robert Muir",
            "id": "comment-13231263"
        },
        {
            "date": "2012-03-16T15:02:51+0000",
            "content": "IndexUpgrader is another example. I think if the args are invalid it should be printing to System.err ?\n\n} else if (\"-dir-impl\".equals(arg)) {\n  if (i == args.length - 1) {\n    System.out.println(\"ERROR: missing value for -dir-impl option\");\n    System.exit(1);\n  }\n\n ",
            "author": "Robert Muir",
            "id": "comment-13231272"
        },
        {
            "date": "2012-03-16T15:18:41+0000",
            "content": "I feel guilty...maybe because I wrote that code  yeah, that one should be System.err.\nI thought at least the command line tool usage could be System.out, but that's already System.err for example in IndexUpgrader, so... looks like everything should be System.err. But that's the behaviour for command line tools. \"Normal\" classes shouldn't have System.err either I guess. Maybe we should mark command line tools as special classes in some way in order to give them more freedom? ",
            "author": "Luca Cavanna",
            "id": "comment-13231286"
        },
        {
            "date": "2012-03-16T15:44:55+0000",
            "content": "I removed the std prints in lucene/core/src/java that I could find on quick grepping.\n\nI'll leave this open so we can somehow automatically catch this... ",
            "author": "Michael McCandless",
            "id": "comment-13231307"
        },
        {
            "date": "2012-03-21T09:48:10+0000",
            "content": "I took a guess that one way would be to replace the System IO streams with ones that will throw exceptions.\n\nIt requires cglib, and might (due to the abuse of sun.reflect.Reflection to get the callee efficiently) be sun hotspot specific.\n\nI guess this is not perfect, it would only error out if the code is called\n\nIf there is thought to this being a good thing I could look into how to wire it up to the unit-tests  ",
            "author": "Greg Bowyer",
            "id": "comment-13234231"
        },
        {
            "date": "2012-03-21T10:05:57+0000",
            "content": "Helps if I upload the right version ",
            "author": "Greg Bowyer",
            "id": "comment-13234248"
        },
        {
            "date": "2012-03-21T19:07:47+0000",
            "content": "You can just as well substitute your own implementation of PrintStream using System.setOut/setErr and check stacks on printlns... But I agree with Benson that a static analysis approach is much cleaner. Don't know if there's anything out of the box in findbugs/ pmd, but even if not then this can be done as a 10-liner by applying an aspect to classes via aspectj and parsing the output logs detecting if an aspect has been applied (it shouldn't match anywhere).  ",
            "author": "Dawid Weiss",
            "id": "comment-13234881"
        },
        {
            "date": "2012-03-21T21:45:26+0000",
            "content": "Thats a good point and started bugging me last night when I was thinking about it.\n\nAs as result attached is a static analysis version that will hate any GETSTATIC java/lang/System::(err|out) (I briefly looked at findbugs and did not find a working version for this idea) \n\nThis one uses ASM 3.3\n\nIts dumb output looks like \n\n/opt/sun-jdk-1.7.0/bin/java -classpath /tmp/test.jar:/tmp/out/production:/tmp/asm-all-3.2.jar SystemPrintCheck /tmp/test.jar\n\nSystemPrintCheck$SystemOutMethodVisitor.visitMethodInsn @ SystemPrintCheck.java +42\nSystemPrintCheck.main @ SystemPrintCheck.java +102\n\nProcess finished with exit code 1 ",
            "author": "Greg Bowyer",
            "id": "comment-13235065"
        },
        {
            "date": "2012-03-21T21:46:07+0000",
            "content": "ASM static test version that dislikes System.out / System.err ",
            "author": "Greg Bowyer",
            "id": "comment-13235067"
        },
        {
            "date": "2012-03-21T22:01:40+0000",
            "content": "fyi. PMD has a rule for this \u2013 SystemPrintln.\nhttp://pmd.sourceforge.net/rules/index.html\n\nDidn't check the details though. ",
            "author": "Dawid Weiss",
            "id": "comment-13235087"
        },
        {
            "date": "2012-03-21T22:08:45+0000",
            "content": "Interesting I didnt look at PMD although that is more down to my personal dislike of code lint tools that do source code analysis\n\nshrugs It was a fun distraction anyhow ",
            "author": "Greg Bowyer",
            "id": "comment-13235090"
        },
        {
            "date": "2012-03-21T22:35:34+0000",
            "content": "I don't like PMD that much either, I'm just saying it seems to have it. If I were to choose though, I'd use aspectj rather than asm-based code. It just seems cleaner to me.\n\npublic aspect NoSysOuts {\n    before(): within(org.apache.lucene..*) && \n              get(static PrintStream System.*) {\n        throw new RuntimeException(\"Attempted sysout/syserr/sysin access.\");\n    }\n}\n\n\nYou don't even need to run it, just weave with verbose output and see if the aspect matched anywhere. ",
            "author": "Dawid Weiss",
            "id": "comment-13235112"
        },
        {
            "date": "2012-03-21T23:29:44+0000",
            "content": "Well would it sway the argument if I said that the ASM code near directly translates into a findbugs rule (I have done this before)\n\nI was also not wanting to suggest findbug custom rules at the start because thats a bigger change in including an entire code lint tool (unless its included with lucene already, in which case forgive my stupidity I am still finding my way around)\n\nSomething doesn't fit right in my mind with the AspectJ approach, I have seen it not work in the past for obscure reasons and it feels that running the weaving in pretend to check the verbose output is not much further on from checking the source code in the first place. ",
            "author": "Greg Bowyer",
            "id": "comment-13235196"
        },
        {
            "date": "2012-03-22T07:40:38+0000",
            "content": "I have seen it not work in the past for obscure reasons\n\nMost likely the \"reasons\" were incorrect pointcut definitions? These can be tricky, I agree. Nonetheless, I've been using AspectJ for a long time and it always fits my needs and expectations. I'm not saying it doesn't have any bugs \u2013 I'm sure it has. But the right tool for the right job; it took me about 5 mins to write and apply that aspect (with follow ups, I sent an e-mail to the mailing list, JIRA didn't work at the time).\n\nI'm not advocating for any tool, really. To me aspectj is a fast tool for expressing where I want a given snippet of code to be injected (or what I want excluded) and for such tasks I don't see a faster or more pleasant to use alternative. Oh, I've been using asmlib too; extensively in fact; so it's not lack of knowledge about the tool itself.\n\n\n ",
            "author": "Dawid Weiss",
            "id": "comment-13235422"
        },
        {
            "date": "2012-03-22T07:51:10+0000",
            "content": "My aspectj experiments from yesterday when JIRA was dead.\n\nI applied that aspect just to see what happens.\n\najc -sourceroots aspects \\\n   -inpath lucene-core-3.6-SNAPSHOT.jar \\\n   -d none \\\n   -cp aspectjrt.jar \\\n   -showWeaveInfo\n\n\nHere's what I got:\n\nJoin point 'field-get(java.io.PrintStream java.lang.System.out)' in\nType 'org.apache.lucene.analysis.PorterStemmer'\n(PorterStemmer.java:529) advised by before advice from\n'spikes.NoSysOuts' (NoSysOuts.aj:6)\n\nJoin point 'field-get(java.io.PrintStream java.lang.System.out)' in\nType 'org.apache.lucene.analysis.PorterStemmer'\n(PorterStemmer.java:534) advised by before advice from\n'spikes.NoSysOuts' (NoSysOuts.aj:6)\n\nJoin point 'field-get(java.io.PrintStream java.lang.System.out)' in\nType 'org.apache.lucene.analysis.PorterStemmer'\n(PorterStemmer.java:542) advised by before advice from\n'spikes.NoSysOuts' (NoSysOuts.aj:6)\n\nJoin point 'field-get(java.io.PrintStream java.lang.System.out)' in\nType 'org.apache.lucene.index.CheckIndex' (CheckIndex.java:989)\nadvised by before advice from 'spikes.NoSysOuts' (NoSysOuts.aj:6)\n\nJoin point 'field-get(java.io.PrintStream java.lang.System.out)' in\nType 'org.apache.lucene.index.CheckIndex' (CheckIndex.java:996)\nadvised by before advice from 'spikes.NoSysOuts' (NoSysOuts.aj:6)\n\nJoin point 'field-get(java.io.PrintStream java.lang.System.out)' in\nType 'org.apache.lucene.index.CheckIndex' (CheckIndex.java:1003)\nadvised by before advice from 'spikes.NoSysOuts' (NoSysOuts.aj:6)\n\nJoin point 'field-get(java.io.PrintStream java.lang.System.out)' in\nType 'org.apache.lucene.index.CheckIndex' (CheckIndex.java:1012)\nadvised by before advice from 'spikes.NoSysOuts' (NoSysOuts.aj:6)\n\nJoin point 'field-get(java.io.PrintStream java.lang.System.out)' in\nType 'org.apache.lucene.index.CheckIndex' (CheckIndex.java:1013)\nadvised by before advice from 'spikes.NoSysOuts' (NoSysOuts.aj:6)\n\nJoin point 'field-get(java.io.PrintStream java.lang.System.out)' in\nType 'org.apache.lucene.index.CheckIndex' (CheckIndex.java:1038)\nadvised by before advice from 'spikes.NoSysOuts' (NoSysOuts.aj:6)\n\nJoin point 'field-get(java.io.PrintStream java.lang.System.out)' in\nType 'org.apache.lucene.index.CheckIndex' (CheckIndex.java:1043)\nadvised by before advice from 'spikes.NoSysOuts' (NoSysOuts.aj:6)\n\nJoin point 'field-get(java.io.PrintStream java.lang.System.out)' in\nType 'org.apache.lucene.index.CheckIndex' (CheckIndex.java:1047)\nadvised by before advice from 'spikes.NoSysOuts' (NoSysOuts.aj:6)\n\nJoin point 'field-get(java.io.PrintStream java.lang.System.out)' in\nType 'org.apache.lucene.index.CheckIndex' (CheckIndex.java:1056)\nadvised by before advice from 'spikes.NoSysOuts' (NoSysOuts.aj:6)\n\nJoin point 'field-get(java.io.PrintStream java.lang.System.out)' in\nType 'org.apache.lucene.index.CheckIndex' (CheckIndex.java:1057)\nadvised by before advice from 'spikes.NoSysOuts' (NoSysOuts.aj:6)\n\nJoin point 'field-get(java.io.PrintStream java.lang.System.out)' in\nType 'org.apache.lucene.index.CheckIndex' (CheckIndex.java:1062)\nadvised by before advice from 'spikes.NoSysOuts' (NoSysOuts.aj:6)\n\nJoin point 'field-get(java.io.PrintStream java.lang.System.out)' in\nType 'org.apache.lucene.index.CheckIndex' (CheckIndex.java:1071)\nadvised by before advice from 'spikes.NoSysOuts' (NoSysOuts.aj:6)\n\nJoin point 'field-get(java.io.PrintStream java.lang.System.out)' in\nType 'org.apache.lucene.index.CheckIndex' (CheckIndex.java:1073)\nadvised by before advice from 'spikes.NoSysOuts' (NoSysOuts.aj:6)\n\nJoin point 'field-get(java.io.PrintStream java.lang.System.out)' in\nType 'org.apache.lucene.index.CheckIndex' (CheckIndex.java:1074)\nadvised by before advice from 'spikes.NoSysOuts' (NoSysOuts.aj:6)\n\nJoin point 'field-get(java.io.PrintStream java.lang.System.out)' in\nType 'org.apache.lucene.index.CheckIndex' (CheckIndex.java:1077)\nadvised by before advice from 'spikes.NoSysOuts' (NoSysOuts.aj:6)\n\nJoin point 'field-get(java.io.PrintStream java.lang.System.out)' in\nType 'org.apache.lucene.index.CheckIndex' (CheckIndex.java:1079)\nadvised by before advice from 'spikes.NoSysOuts' (NoSysOuts.aj:6)\n\nJoin point 'field-get(java.io.PrintStream java.lang.System.out)' in\nType 'org.apache.lucene.index.CheckIndex' (CheckIndex.java:1081)\nadvised by before advice from 'spikes.NoSysOuts' (NoSysOuts.aj:6)\n\nJoin point 'field-get(java.io.PrintStream java.lang.System.out)' in\nType 'org.apache.lucene.index.CheckIndex' (CheckIndex.java:1082)\nadvised by before advice from 'spikes.NoSysOuts' (NoSysOuts.aj:6)\n\nJoin point 'field-get(java.io.PrintStream java.lang.System.out)' in\nType 'org.apache.lucene.index.CheckIndex' (CheckIndex.java:1085)\nadvised by before advice from 'spikes.NoSysOuts' (NoSysOuts.aj:6)\n\nJoin point 'field-get(java.io.PrintStream java.lang.System.err)' in\nType 'org.apache.lucene.index.IndexUpgrader' (IndexUpgrader.java:55)\nadvised by before advice from 'spikes.NoSysOuts' (NoSysOuts.aj:6)\n\nJoin point 'field-get(java.io.PrintStream java.lang.System.err)' in\nType 'org.apache.lucene.index.IndexUpgrader' (IndexUpgrader.java:56)\nadvised by before advice from 'spikes.NoSysOuts' (NoSysOuts.aj:6)\n\nJoin point 'field-get(java.io.PrintStream java.lang.System.err)' in\nType 'org.apache.lucene.index.IndexUpgrader' (IndexUpgrader.java:57)\nadvised by before advice from 'spikes.NoSysOuts' (NoSysOuts.aj:6)\n\nJoin point 'field-get(java.io.PrintStream java.lang.System.err)' in\nType 'org.apache.lucene.index.IndexUpgrader' (IndexUpgrader.java:58)\nadvised by before advice from 'spikes.NoSysOuts' (NoSysOuts.aj:6)\n\nJoin point 'field-get(java.io.PrintStream java.lang.System.err)' in\nType 'org.apache.lucene.index.IndexUpgrader' (IndexUpgrader.java:59)\nadvised by before advice from 'spikes.NoSysOuts' (NoSysOuts.aj:6)\n\nJoin point 'field-get(java.io.PrintStream java.lang.System.err)' in\nType 'org.apache.lucene.index.IndexUpgrader' (IndexUpgrader.java:60)\nadvised by before advice from 'spikes.NoSysOuts' (NoSysOuts.aj:6)\n\nJoin point 'field-get(java.io.PrintStream java.lang.System.err)' in\nType 'org.apache.lucene.index.IndexUpgrader' (IndexUpgrader.java:61)\nadvised by before advice from 'spikes.NoSysOuts' (NoSysOuts.aj:6)\n\nJoin point 'field-get(java.io.PrintStream java.lang.System.err)' in\nType 'org.apache.lucene.index.IndexUpgrader' (IndexUpgrader.java:62)\nadvised by before advice from 'spikes.NoSysOuts' (NoSysOuts.aj:6)\n\nJoin point 'field-get(java.io.PrintStream java.lang.System.err)' in\nType 'org.apache.lucene.index.IndexUpgrader' (IndexUpgrader.java:65)\nadvised by before advice from 'spikes.NoSysOuts' (NoSysOuts.aj:6)\n\nJoin point 'field-get(java.io.PrintStream java.lang.System.out)' in\nType 'org.apache.lucene.index.IndexUpgrader' (IndexUpgrader.java:81)\nadvised by before advice from 'spikes.NoSysOuts' (NoSysOuts.aj:6)\n\nJoin point 'field-get(java.io.PrintStream java.lang.System.out)' in\nType 'org.apache.lucene.index.IndexUpgrader' (IndexUpgrader.java:86)\nadvised by before advice from 'spikes.NoSysOuts' (NoSysOuts.aj:6)\n\nJoin point 'field-get(java.io.PrintStream java.lang.System.err)' in\nType 'org.apache.lucene.queryParser.FastCharStream'\n(FastCharStream.java:102) advised by before advice from\n'spikes.NoSysOuts' (NoSysOuts.aj:6)\n\nJoin point 'field-get(java.io.PrintStream java.lang.System.out)' in\nType 'org.apache.lucene.queryParser.QueryParser'\n(QueryParser.java:1159) advised by before advice from\n'spikes.NoSysOuts' (NoSysOuts.aj:6)\n\nJoin point 'field-get(java.io.PrintStream java.lang.System.out)' in\nType 'org.apache.lucene.queryParser.QueryParser'\n(QueryParser.java:1165) advised by before advice from\n'spikes.NoSysOuts' (NoSysOuts.aj:6)\n\nJoin point 'field-get(java.io.PrintStream java.lang.System.out)' in\nType 'org.apache.lucene.queryParser.QueryParserTokenManager'\n(QueryParserTokenManager.java:42) advised by before advice from\n'spikes.NoSysOuts' (NoSysOuts.aj:6)\n\nJoin point 'field-get(java.io.PrintStream java.lang.System.out)' in\nType 'org.apache.lucene.store.LockStressTest' (LockStressTest.java:37)\nadvised by before advice from 'spikes.NoSysOuts' (NoSysOuts.aj:6)\n\nJoin point 'field-get(java.io.PrintStream java.lang.System.out)' in\nType 'org.apache.lucene.store.LockStressTest' (LockStressTest.java:58)\nadvised by before advice from 'spikes.NoSysOuts' (NoSysOuts.aj:6)\n\nJoin point 'field-get(java.io.PrintStream java.lang.System.out)' in\nType 'org.apache.lucene.store.LockStressTest'\n(LockStressTest.java:100) advised by before advice from\n'spikes.NoSysOuts' (NoSysOuts.aj:6)\n\nJoin point 'field-get(java.io.PrintStream java.lang.System.out)' in\nType 'org.apache.lucene.store.LockStressTest'\n(LockStressTest.java:104) advised by before advice from\n'spikes.NoSysOuts' (NoSysOuts.aj:6)\n\nJoin point 'field-get(java.io.PrintStream java.lang.System.out)' in\nType 'org.apache.lucene.store.LockVerifyServer'\n(LockVerifyServer.java:45) advised by before advice from\n'spikes.NoSysOuts' (NoSysOuts.aj:6)\n\nJoin point 'field-get(java.io.PrintStream java.lang.System.out)' in\nType 'org.apache.lucene.store.LockVerifyServer'\n(LockVerifyServer.java:53) advised by before advice from\n'spikes.NoSysOuts' (NoSysOuts.aj:6)\n\nJoin point 'field-get(java.io.PrintStream java.lang.System.out)' in\nType 'org.apache.lucene.store.LockVerifyServer'\n(LockVerifyServer.java:72) advised by before advice from\n'spikes.NoSysOuts' (NoSysOuts.aj:6)\n\nJoin point 'field-get(java.io.PrintStream java.lang.System.out)' in\nType 'org.apache.lucene.store.LockVerifyServer'\n(LockVerifyServer.java:78) advised by before advice from\n'spikes.NoSysOuts' (NoSysOuts.aj:6)\n\nJoin point 'field-get(java.io.PrintStream java.lang.System.out)' in\nType 'org.apache.lucene.store.LockVerifyServer'\n(LockVerifyServer.java:84) advised by before advice from\n'spikes.NoSysOuts' (NoSysOuts.aj:6)\n\n\nMany of these are in static main methods and here's where\naspectj-based solution can be superior to handcoding; because we can\ndo this:\n\n   pointcut ignored():\n       withincode(public static void main(String[]));\n\n   before(): within(org.apache.lucene..*) &&\n             get(static PrintStream System.*) &&\n             !ignored()\n   {\n       throw new RuntimeException(\"Attempted sysout/syserr/sysin access.\");\n   }\n\n\napplied again:\n\nJoin point 'field-get(java.io.PrintStream java.lang.System.err)' in\nType 'org.apache.lucene.index.IndexUpgrader' (IndexUpgrader.java:55)\nadvised by before advice from 'spikes.NoSysOuts' (NoSysOuts.aj:16)\n\nJoin point 'field-get(java.io.PrintStream java.lang.System.err)' in\nType 'org.apache.lucene.index.IndexUpgrader' (IndexUpgrader.java:56)\nadvised by before advice from 'spikes.NoSysOuts' (NoSysOuts.aj:16)\n\nJoin point 'field-get(java.io.PrintStream java.lang.System.err)' in\nType 'org.apache.lucene.index.IndexUpgrader' (IndexUpgrader.java:57)\nadvised by before advice from 'spikes.NoSysOuts' (NoSysOuts.aj:16)\n\nJoin point 'field-get(java.io.PrintStream java.lang.System.err)' in\nType 'org.apache.lucene.index.IndexUpgrader' (IndexUpgrader.java:58)\nadvised by before advice from 'spikes.NoSysOuts' (NoSysOuts.aj:16)\n\nJoin point 'field-get(java.io.PrintStream java.lang.System.err)' in\nType 'org.apache.lucene.index.IndexUpgrader' (IndexUpgrader.java:59)\nadvised by before advice from 'spikes.NoSysOuts' (NoSysOuts.aj:16)\n\nJoin point 'field-get(java.io.PrintStream java.lang.System.err)' in\nType 'org.apache.lucene.index.IndexUpgrader' (IndexUpgrader.java:60)\nadvised by before advice from 'spikes.NoSysOuts' (NoSysOuts.aj:16)\n\nJoin point 'field-get(java.io.PrintStream java.lang.System.err)' in\nType 'org.apache.lucene.index.IndexUpgrader' (IndexUpgrader.java:61)\nadvised by before advice from 'spikes.NoSysOuts' (NoSysOuts.aj:16)\n\nJoin point 'field-get(java.io.PrintStream java.lang.System.err)' in\nType 'org.apache.lucene.index.IndexUpgrader' (IndexUpgrader.java:62)\nadvised by before advice from 'spikes.NoSysOuts' (NoSysOuts.aj:16)\n\nJoin point 'field-get(java.io.PrintStream java.lang.System.err)' in\nType 'org.apache.lucene.index.IndexUpgrader' (IndexUpgrader.java:65)\nadvised by before advice from 'spikes.NoSysOuts' (NoSysOuts.aj:16)\n\nJoin point 'field-get(java.io.PrintStream java.lang.System.err)' in\nType 'org.apache.lucene.queryParser.FastCharStream'\n(FastCharStream.java:102) advised by before advice from\n'spikes.NoSysOuts' (NoSysOuts.aj:16)\n\nJoin point 'field-get(java.io.PrintStream java.lang.System.out)' in\nType 'org.apache.lucene.queryParser.QueryParserTokenManager'\n(QueryParserTokenManager.java:42) advised by before advice from\n'spikes.NoSysOuts' (NoSysOuts.aj:16)\n\n\nIndexUpgrader has a printUsage() method so we can exclude these by\nname only (no access/ static restriction):\n\n   pointcut ignored():\n       withincode(public static void main(String[])) ||\n       withincode(              void printUsage(..));\n\n\nand then we're left with:\n\nJoin point 'field-get(java.io.PrintStream java.lang.System.err)' in\nType 'org.apache.lucene.queryParser.FastCharStream'\n(FastCharStream.java:102) advised by before advice from\n'spikes.NoSysOuts' (NoSysOuts.aj:17)\n\nJoin point 'field-get(java.io.PrintStream java.lang.System.out)' in\nType 'org.apache.lucene.queryParser.QueryParserTokenManager'\n(QueryParserTokenManager.java:42) advised by before advice from\n'spikes.NoSysOuts' (NoSysOuts.aj:17)\n\n\nand these are:\n\n   } catch (IOException e) {\n     System.err.println(\"Caught: \" + e + \"; ignoring.\");\n   }\n\n\nand:\n\n /** Debug output. */\n public  java.io.PrintStream debugStream = System.out;\n\n\nThis is perhaps the worst cast as it assigns System.out to another\nfield and then uses that to call printlns.\n\nBoth of which can be excluded, of course. AspectJ is fun. It's a pity\nit never gained more traction. ",
            "author": "Dawid Weiss",
            "id": "comment-13235424"
        },
        {
            "date": "2012-03-22T07:53:28+0000",
            "content": "Oh, btw. I think a FindBugs rule for detecting sysouts/syserrs would be a great addition to FindBugs \u2013 you should definitely file it as an improvement there. In reality at least class-level exclusions will be needed to avoid legitimate matches like the ones shown above (main methods, exception handlers), but these can be lived with. ",
            "author": "Dawid Weiss",
            "id": "comment-13235428"
        },
        {
            "date": "2012-03-23T20:40:19+0000",
            "content": "Issue is marked 3.6 and actively being discussed but has no assignee - assigning to most active committer contributing patches/discussion so far to triage wether this can/should be pushed to 4.0 or not. ",
            "author": "Hoss Man",
            "id": "comment-13237094"
        },
        {
            "date": "2012-03-23T21:00:47+0000",
            "content": "I'd push it to 4.0 (automation in whatever form). ",
            "author": "Dawid Weiss",
            "id": "comment-13237117"
        },
        {
            "date": "2012-03-24T01:14:31+0000",
            "content": "Yeah sorry I have been busy at work for a spell, I was going to craft it into a findbugs rule and see if I can get accepted into the findbugs project,\n\nJust been a bit tied up thats all ",
            "author": "Greg Bowyer",
            "id": "comment-13237380"
        },
        {
            "date": "2012-03-24T08:34:40+0000",
            "content": "No worries Greg, really. For 3.x I think manual check will do (or what I've done above with AspectJ). For 4.x it'd be nice to have findbugs lint anyway (for this and other issues). It'll most likely require some rules tuning too, so it can be a separate issue. ",
            "author": "Dawid Weiss",
            "id": "comment-13237479"
        },
        {
            "date": "2012-07-09T19:17:43+0000",
            "content": "I think if we fix LUCENE-4202, we could just have a separate task for this that only runs on a fileset of non-test code? We could also exclude some tools like CheckIndex from it.\n\nWe could add things like:\nSystem#in\nSystem#out\nSystem#err\nThrowable#printStackTrace() <-- eclipse stupid-stubs\n... ",
            "author": "Robert Muir",
            "id": "comment-13409751"
        },
        {
            "date": "2012-07-10T12:02:32+0000",
            "content": "Here's a patch implementing this check with LUCENE-4202. It excludes any test code, but I didnt add any exceptions for legitimate command-line tools.\n\nCurrent list looks like:\n\ncheck-system-out:\n[forbidden-apis] Reading inline API signatures...\n[forbidden-apis] Reading API signatures: /home/rmuir/workspace/lucene-trunk/lucene/tools/forbiddenApis/system-out.txt\n[forbidden-apis] Forbidden field access: java.lang.System#out\n[forbidden-apis]   in org.apache.lucene.analysis.compound.hyphenation.HyphenationTree (HyphenationTree.java:467)\n[forbidden-apis] Forbidden field access: java.lang.System#out\n[forbidden-apis]   in org.apache.lucene.analysis.compound.hyphenation.PatternParser (PatternParser.java:408)\n[forbidden-apis] Forbidden field access: java.lang.System#out\n[forbidden-apis]   in org.apache.lucene.analysis.compound.hyphenation.PatternParser (PatternParser.java:412)\n[forbidden-apis] Forbidden field access: java.lang.System#out\n[forbidden-apis]   in org.apache.lucene.analysis.compound.hyphenation.PatternParser (PatternParser.java:416)\n[forbidden-apis] Forbidden field access: java.lang.System#out\n[forbidden-apis]   in org.apache.lucene.analysis.compound.hyphenation.TernaryTree (TernaryTree.java:637)\n[forbidden-apis] Forbidden field access: java.lang.System#out\n[forbidden-apis]   in org.apache.lucene.analysis.compound.hyphenation.TernaryTree (TernaryTree.java:638)\n[forbidden-apis] Forbidden field access: java.lang.System#out\n[forbidden-apis]   in org.apache.lucene.analysis.compound.hyphenation.TernaryTree (TernaryTree.java:640)\n[forbidden-apis] Forbidden field access: java.lang.System#out\n[forbidden-apis]   in org.apache.lucene.analysis.compound.hyphenation.TernaryTree (TernaryTree.java:658)\n[forbidden-apis] Forbidden field access: java.lang.System#out\n[forbidden-apis]   in org.apache.lucene.analysis.compound.hyphenation.TernaryTree (TernaryTree.java:659)\n[forbidden-apis] Forbidden field access: java.lang.System#out\n[forbidden-apis]   in org.apache.lucene.analysis.compound.hyphenation.TernaryTree (TernaryTree.java:660)\n[forbidden-apis] Forbidden field access: java.lang.System#out\n[forbidden-apis]   in org.apache.lucene.analysis.en.KStemmer (KStemmer.java:292)\n[forbidden-apis] Forbidden field access: java.lang.System#out\n[forbidden-apis]   in org.apache.lucene.analysis.en.KStemmer (KStemmer.java:302)\n[forbidden-apis] Forbidden field access: java.lang.System#out\n[forbidden-apis]   in org.apache.lucene.analysis.en.KStemmer (KStemmer.java:312)\n[forbidden-apis] Forbidden field access: java.lang.System#out\n[forbidden-apis]   in org.apache.lucene.analysis.en.KStemmer (KStemmer.java:326)\n[forbidden-apis] Forbidden field access: java.lang.System#out\n[forbidden-apis]   in org.apache.lucene.analysis.en.KStemmer (KStemmer.java:336)\n[forbidden-apis] Forbidden field access: java.lang.System#out\n[forbidden-apis]   in org.apache.lucene.analysis.en.KStemmer (KStemmer.java:346)\n[forbidden-apis] Forbidden field access: java.lang.System#out\n[forbidden-apis]   in org.apache.lucene.analysis.en.KStemmer (KStemmer.java:356)\n[forbidden-apis] Forbidden field access: java.lang.System#out\n[forbidden-apis]   in org.apache.lucene.analysis.en.KStemmer (KStemmer.java:366)\n[forbidden-apis] Forbidden field access: java.lang.System#out\n[forbidden-apis]   in org.apache.lucene.analysis.en.KStemmer (KStemmer.java:376)\n[forbidden-apis] Forbidden field access: java.lang.System#out\n[forbidden-apis]   in org.apache.lucene.analysis.en.KStemmer (KStemmer.java:386)\n[forbidden-apis] Forbidden field access: java.lang.System#out\n[forbidden-apis]   in org.apache.lucene.analysis.en.KStemmer (KStemmer.java:395)\n[forbidden-apis] Forbidden field access: java.lang.System#out\n[forbidden-apis]   in org.apache.lucene.analysis.en.KStemmer (KStemmer.java:404)\n[forbidden-apis] Forbidden field access: java.lang.System#out\n[forbidden-apis]   in org.apache.lucene.analysis.en.KStemmer (KStemmer.java:413)\n[forbidden-apis] Forbidden field access: java.lang.System#out\n[forbidden-apis]   in org.apache.lucene.analysis.en.PorterStemmer (PorterStemmer.java:529)\n[forbidden-apis] Forbidden field access: java.lang.System#out\n[forbidden-apis]   in org.apache.lucene.analysis.en.PorterStemmer (PorterStemmer.java:534)\n[forbidden-apis] Forbidden field access: java.lang.System#out\n[forbidden-apis]   in org.apache.lucene.analysis.en.PorterStemmer (PorterStemmer.java:542)\n[forbidden-apis] Forbidden field access: java.lang.System#out\n[forbidden-apis]   in org.apache.lucene.analysis.hunspell.HunspellStemmer (HunspellStemmer.java:314)\n[forbidden-apis] Forbidden field access: java.lang.System#out\n[forbidden-apis]   in org.apache.lucene.analysis.hunspell.HunspellStemmer (HunspellStemmer.java:320)\n[forbidden-apis] Forbidden field access: java.lang.System#out\n[forbidden-apis]   in org.apache.lucene.analysis.hunspell.HunspellStemmer (HunspellStemmer.java:336)\n[forbidden-apis] Forbidden field access: java.lang.System#out\n[forbidden-apis]   in org.apache.lucene.analysis.hunspell.HunspellStemmer (HunspellStemmer.java:346)\n[forbidden-apis] Forbidden field access: java.lang.System#out\n[forbidden-apis]   in org.apache.lucene.analysis.hunspell.HunspellStemmer (HunspellStemmer.java:382)\n[forbidden-apis] Forbidden field access: java.lang.System#err\n[forbidden-apis]   in org.apache.lucene.analysis.pt.RSLPStemmerBase$RuleWithSetExceptions (RSLPStemmerBase.java:135)\n[forbidden-apis] Forbidden field access: java.lang.System#err\n[forbidden-apis]   in org.apache.lucene.analysis.pt.RSLPStemmerBase$RuleWithSuffixExceptions (RSLPStemmerBase.java:159)\n[forbidden-apis] Forbidden field access: java.lang.System#err\n[forbidden-apis]   in org.tartarus.snowball.SnowballProgram (SnowballProgram.java:438)\n[forbidden-apis] Forbidden field access: java.lang.System#err\n[forbidden-apis]   in org.apache.lucene.analysis.cn.smart.AnalyzerProfile (AnalyzerProfile.java:69)\n[forbidden-apis] Forbidden field access: java.lang.System#err\n[forbidden-apis]   in org.apache.lucene.analysis.cn.smart.AnalyzerProfile (AnalyzerProfile.java:71)\n[forbidden-apis] Forbidden field access: java.lang.System#err\n[forbidden-apis]   in org.apache.lucene.analysis.cn.smart.AnalyzerProfile (AnalyzerProfile.java:73)\n[forbidden-apis] Forbidden field access: java.lang.System#out\n[forbidden-apis]   in org.egothor.stemmer.Compile (Compile.java:126)\n[forbidden-apis] Forbidden field access: java.lang.System#out\n[forbidden-apis]   in org.egothor.stemmer.DiffIt (DiffIt.java:107)\n[forbidden-apis] Forbidden field access: java.lang.System#out\n[forbidden-apis]   in org.egothor.stemmer.DiffIt (DiffIt.java:111)\n[forbidden-apis] Forbidden field access: java.lang.System#out\n[forbidden-apis]   in org.egothor.stemmer.Row (Row.java:301)\n[forbidden-apis] Forbidden field access: java.lang.System#out\n[forbidden-apis]   in org.egothor.stemmer.Row (Row.java:303)\n[forbidden-apis] Forbidden field access: java.lang.System#out\n[forbidden-apis]   in org.egothor.stemmer.Trie (Trie.java:379)\n[forbidden-apis] Forbidden field access: java.lang.System#err\n[forbidden-apis]   in org.apache.lucene.benchmark.byTask.Benchmark (Benchmark.java:95)\n[forbidden-apis] Forbidden field access: java.lang.System#err\n[forbidden-apis]   in org.apache.lucene.benchmark.byTask.Benchmark (Benchmark.java:102)\n[forbidden-apis] Forbidden field access: java.lang.System#out\n[forbidden-apis]   in org.apache.lucene.benchmark.byTask.Benchmark (Benchmark.java:106)\n[forbidden-apis] Forbidden field access: java.lang.System#out\n[forbidden-apis]   in org.apache.lucene.benchmark.byTask.Benchmark (Benchmark.java:116)\n[forbidden-apis] Forbidden field access: java.lang.System#out\n[forbidden-apis]   in org.apache.lucene.benchmark.byTask.Benchmark (Benchmark.java:117)\n[forbidden-apis] Forbidden field access: java.lang.System#err\n[forbidden-apis]   in org.apache.lucene.benchmark.byTask.Benchmark (Benchmark.java:123)\n[forbidden-apis] Forbidden field access: java.lang.System#out\n[forbidden-apis]   in org.apache.lucene.benchmark.byTask.Benchmark (Benchmark.java:127)\n[forbidden-apis] Forbidden field access: java.lang.System#out\n[forbidden-apis]   in org.apache.lucene.benchmark.byTask.Benchmark (Benchmark.java:128)\n[forbidden-apis] Forbidden field access: java.lang.System#out\n[forbidden-apis]   in org.apache.lucene.benchmark.byTask.Benchmark (Benchmark.java:129)\n[forbidden-apis] Forbidden field access: java.lang.System#out\n[forbidden-apis]   in org.apache.lucene.benchmark.byTask.PerfRunData (PerfRunData.java:134)\n[forbidden-apis] Forbidden field access: java.lang.System#out\n[forbidden-apis]   in org.apache.lucene.benchmark.byTask.PerfRunData (PerfRunData.java:135)\n[forbidden-apis] Forbidden field access: java.lang.System#out\n[forbidden-apis]   in org.apache.lucene.benchmark.byTask.feeds.ContentItemsSource (ContentItemsSource.java:178)\n[forbidden-apis] Forbidden field access: java.lang.System#out\n[forbidden-apis]   in org.apache.lucene.benchmark.byTask.feeds.DemoHTMLParser (DemoHTMLParser.java:58)\n[forbidden-apis] Forbidden field access: java.lang.System#err\n[forbidden-apis]   in org.apache.lucene.benchmark.byTask.feeds.EnwikiQueryMaker (EnwikiQueryMaker.java:110)\n[forbidden-apis] Forbidden field access: java.lang.System#err\n[forbidden-apis]   in org.apache.lucene.benchmark.byTask.feeds.FileBasedQueryMaker (FileBasedQueryMaker.java:84)\n[forbidden-apis] Forbidden field access: java.lang.System#err\n[forbidden-apis]   in org.apache.lucene.benchmark.byTask.feeds.FileBasedQueryMaker (FileBasedQueryMaker.java:93)\n[forbidden-apis] Forbidden field access: java.lang.System#err\n[forbidden-apis]   in org.apache.lucene.benchmark.byTask.feeds.ReutersQueryMaker (ReutersQueryMaker.java:90)\n[forbidden-apis] Forbidden field access: java.lang.System#out\n[forbidden-apis]   in org.apache.lucene.benchmark.byTask.feeds.TrecContentSource (TrecContentSource.java:195)\n[forbidden-apis] Forbidden field access: java.lang.System#out\n[forbidden-apis]   in org.apache.lucene.benchmark.byTask.feeds.TrecContentSource (TrecContentSource.java:204)\n[forbidden-apis] Forbidden field access: java.lang.System#out\n[forbidden-apis]   in org.apache.lucene.benchmark.byTask.feeds.TrecContentSource (TrecContentSource.java:227)\n[forbidden-apis] Forbidden field access: java.lang.System#out\n[forbidden-apis]   in org.apache.lucene.benchmark.byTask.feeds.TrecContentSource (TrecContentSource.java:242)\n[forbidden-apis] Forbidden field access: java.lang.System#out\n[forbidden-apis]   in org.apache.lucene.benchmark.byTask.feeds.TrecContentSource (TrecContentSource.java:243)\n[forbidden-apis] Forbidden field access: java.lang.System#out\n[forbidden-apis]   in org.apache.lucene.benchmark.byTask.feeds.demohtml.HTMLParserTokenManager (HTMLParserTokenManager.java:12)\n[forbidden-apis] Forbidden field access: java.lang.System#out\n[forbidden-apis]   in org.apache.lucene.benchmark.byTask.feeds.demohtml.ParserThread (ParserThread.java:35)\n[forbidden-apis] Forbidden field access: java.lang.System#out\n[forbidden-apis]   in org.apache.lucene.benchmark.byTask.feeds.demohtml.ParserThread (ParserThread.java:37)\n[forbidden-apis] Forbidden field access: java.lang.System#out\n[forbidden-apis]   in org.apache.lucene.benchmark.byTask.programmatic.Sample (Sample.java:72)\n[forbidden-apis] Forbidden field access: java.lang.System#out\n[forbidden-apis]   in org.apache.lucene.benchmark.byTask.tasks.CloseReaderTask (CloseReaderTask.java:41)\n[forbidden-apis] Forbidden field access: java.lang.System#out\n[forbidden-apis]   in org.apache.lucene.benchmark.byTask.tasks.CloseTaxonomyReaderTask (CloseTaxonomyReaderTask.java:40)\n[forbidden-apis] Forbidden field access: java.lang.System#out\n[forbidden-apis]   in org.apache.lucene.benchmark.byTask.tasks.CreateIndexTask (CreateIndexTask.java:181)\n[forbidden-apis] Forbidden field access: java.lang.System#err\n[forbidden-apis]   in org.apache.lucene.benchmark.byTask.tasks.CreateIndexTask (CreateIndexTask.java:183)\n[forbidden-apis] Forbidden field access: java.lang.System#out\n[forbidden-apis]   in org.apache.lucene.benchmark.byTask.tasks.NearRealtimeReaderTask (NearRealtimeReaderTask.java:108)\n[forbidden-apis] Forbidden field access: java.lang.System#out\n[forbidden-apis]   in org.apache.lucene.benchmark.byTask.tasks.NearRealtimeReaderTask (NearRealtimeReaderTask.java:110)\n[forbidden-apis] Forbidden field access: java.lang.System#out\n[forbidden-apis]   in org.apache.lucene.benchmark.byTask.tasks.NearRealtimeReaderTask (NearRealtimeReaderTask.java:112)\n[forbidden-apis] Forbidden field access: java.lang.System#out\n[forbidden-apis]   in org.apache.lucene.benchmark.byTask.tasks.NewAnalyzerTask (NewAnalyzerTask.java:81)\n[forbidden-apis] Forbidden field access: java.lang.System#out\n[forbidden-apis]   in org.apache.lucene.benchmark.byTask.tasks.NewCollationAnalyzerTask (NewCollationAnalyzerTask.java:88)\n[forbidden-apis] Forbidden field access: java.lang.System#out\n[forbidden-apis]   in org.apache.lucene.benchmark.byTask.tasks.NewLocaleTask (NewLocaleTask.java:66)\n[forbidden-apis] Forbidden field access: java.lang.System#out\n[forbidden-apis]   in org.apache.lucene.benchmark.byTask.tasks.NewShingleAnalyzerTask (NewShingleAnalyzerTask.java:83)\n[forbidden-apis] Forbidden field access: java.lang.System#out\n[forbidden-apis]   in org.apache.lucene.benchmark.byTask.tasks.PerfTask (PerfTask.java:138)\n[forbidden-apis] Forbidden field access: java.lang.System#out\n[forbidden-apis]   in org.apache.lucene.benchmark.byTask.tasks.PerfTask (PerfTask.java:271)\n[forbidden-apis] Forbidden field access: java.lang.System#out\n[forbidden-apis]   in org.apache.lucene.benchmark.byTask.tasks.PrintReaderTask (PrintReaderTask.java:54)\n[forbidden-apis] Forbidden field access: java.lang.System#out\n[forbidden-apis]   in org.apache.lucene.benchmark.byTask.tasks.ReadTask (ReadTask.java:140)\n[forbidden-apis] Forbidden field access: java.lang.System#out\n[forbidden-apis]   in org.apache.lucene.benchmark.byTask.tasks.ReadTask (ReadTask.java:141)\n[forbidden-apis] Forbidden field access: java.lang.System#out\n[forbidden-apis]   in org.apache.lucene.benchmark.byTask.tasks.ReadTask (ReadTask.java:142)\n[forbidden-apis] Forbidden field access: java.lang.System#out\n[forbidden-apis]   in org.apache.lucene.benchmark.byTask.tasks.ReadTask (ReadTask.java:146)\n[forbidden-apis] Forbidden field access: java.lang.System#out\n[forbidden-apis]   in org.apache.lucene.benchmark.byTask.tasks.RepAllTask (RepAllTask.java:40)\n[forbidden-apis] Forbidden field access: java.lang.System#out\n[forbidden-apis]   in org.apache.lucene.benchmark.byTask.tasks.RepAllTask (RepAllTask.java:41)\n[forbidden-apis] Forbidden field access: java.lang.System#out\n[forbidden-apis]   in org.apache.lucene.benchmark.byTask.tasks.RepAllTask (RepAllTask.java:42)\n[forbidden-apis] Forbidden field access: java.lang.System#out\n[forbidden-apis]   in org.apache.lucene.benchmark.byTask.tasks.RepAllTask (RepAllTask.java:43)\n[forbidden-apis] Forbidden field access: java.lang.System#out\n[forbidden-apis]   in org.apache.lucene.benchmark.byTask.tasks.RepSelectByPrefTask (RepSelectByPrefTask.java:40)\n[forbidden-apis] Forbidden field access: java.lang.System#out\n[forbidden-apis]   in org.apache.lucene.benchmark.byTask.tasks.RepSelectByPrefTask (RepSelectByPrefTask.java:41)\n[forbidden-apis] Forbidden field access: java.lang.System#out\n[forbidden-apis]   in org.apache.lucene.benchmark.byTask.tasks.RepSelectByPrefTask (RepSelectByPrefTask.java:43)\n[forbidden-apis] Forbidden field access: java.lang.System#out\n[forbidden-apis]   in org.apache.lucene.benchmark.byTask.tasks.RepSelectByPrefTask (RepSelectByPrefTask.java:44)\n[forbidden-apis] Forbidden field access: java.lang.System#out\n[forbidden-apis]   in org.apache.lucene.benchmark.byTask.tasks.RepSumByNameRoundTask (RepSumByNameRoundTask.java:41)\n[forbidden-apis] Forbidden field access: java.lang.System#out\n[forbidden-apis]   in org.apache.lucene.benchmark.byTask.tasks.RepSumByNameRoundTask (RepSumByNameRoundTask.java:42)\n[forbidden-apis] Forbidden field access: java.lang.System#out\n[forbidden-apis]   in org.apache.lucene.benchmark.byTask.tasks.RepSumByNameRoundTask (RepSumByNameRoundTask.java:44)\n[forbidden-apis] Forbidden field access: java.lang.System#out\n[forbidden-apis]   in org.apache.lucene.benchmark.byTask.tasks.RepSumByNameRoundTask (RepSumByNameRoundTask.java:45)\n[forbidden-apis] Forbidden field access: java.lang.System#out\n[forbidden-apis]   in org.apache.lucene.benchmark.byTask.tasks.RepSumByNameTask (RepSumByNameTask.java:41)\n[forbidden-apis] Forbidden field access: java.lang.System#out\n[forbidden-apis]   in org.apache.lucene.benchmark.byTask.tasks.RepSumByNameTask (RepSumByNameTask.java:42)\n[forbidden-apis] Forbidden field access: java.lang.System#out\n[forbidden-apis]   in org.apache.lucene.benchmark.byTask.tasks.RepSumByNameTask (RepSumByNameTask.java:44)\n[forbidden-apis] Forbidden field access: java.lang.System#out\n[forbidden-apis]   in org.apache.lucene.benchmark.byTask.tasks.RepSumByNameTask (RepSumByNameTask.java:45)\n[forbidden-apis] Forbidden field access: java.lang.System#out\n[forbidden-apis]   in org.apache.lucene.benchmark.byTask.tasks.RepSumByPrefRoundTask (RepSumByPrefRoundTask.java:41)\n[forbidden-apis] Forbidden field access: java.lang.System#out\n[forbidden-apis]   in org.apache.lucene.benchmark.byTask.tasks.RepSumByPrefRoundTask (RepSumByPrefRoundTask.java:42)\n[forbidden-apis] Forbidden field access: java.lang.System#out\n[forbidden-apis]   in org.apache.lucene.benchmark.byTask.tasks.RepSumByPrefRoundTask (RepSumByPrefRoundTask.java:44)\n[forbidden-apis] Forbidden field access: java.lang.System#out\n[forbidden-apis]   in org.apache.lucene.benchmark.byTask.tasks.RepSumByPrefRoundTask (RepSumByPrefRoundTask.java:45)\n[forbidden-apis] Forbidden field access: java.lang.System#out\n[forbidden-apis]   in org.apache.lucene.benchmark.byTask.tasks.RepSumByPrefTask (RepSumByPrefTask.java:43)\n[forbidden-apis] Forbidden field access: java.lang.System#out\n[forbidden-apis]   in org.apache.lucene.benchmark.byTask.tasks.RepSumByPrefTask (RepSumByPrefTask.java:44)\n[forbidden-apis] Forbidden field access: java.lang.System#out\n[forbidden-apis]   in org.apache.lucene.benchmark.byTask.tasks.RepSumByPrefTask (RepSumByPrefTask.java:46)\n[forbidden-apis] Forbidden field access: java.lang.System#out\n[forbidden-apis]   in org.apache.lucene.benchmark.byTask.tasks.RepSumByPrefTask (RepSumByPrefTask.java:47)\n[forbidden-apis] Forbidden field access: java.lang.System#out\n[forbidden-apis]   in org.apache.lucene.benchmark.byTask.utils.Config (Config.java:117)\n[forbidden-apis] Forbidden field access: java.lang.System#out\n[forbidden-apis]   in org.apache.lucene.benchmark.byTask.utils.Config (Config.java:121)\n[forbidden-apis] Forbidden field access: java.lang.System#out\n[forbidden-apis]   in org.apache.lucene.benchmark.byTask.utils.Config (Config.java:123)\n[forbidden-apis] Forbidden field access: java.lang.System#out\n[forbidden-apis]   in org.apache.lucene.benchmark.byTask.utils.Config (Config.java:307)\n[forbidden-apis] Forbidden field access: java.lang.System#out\n[forbidden-apis]   in org.apache.lucene.benchmark.byTask.utils.Config (Config.java:308)\n[forbidden-apis] Forbidden field access: java.lang.System#out\n[forbidden-apis]   in org.apache.lucene.benchmark.byTask.utils.Config (Config.java:309)\n[forbidden-apis] Forbidden field access: java.lang.System#err\n[forbidden-apis]   in org.apache.lucene.benchmark.quality.trec.QueryDriver (QueryDriver.java:44)\n[forbidden-apis] Forbidden field access: java.lang.System#err\n[forbidden-apis]   in org.apache.lucene.benchmark.quality.trec.QueryDriver (QueryDriver.java:45)\n[forbidden-apis] Forbidden field access: java.lang.System#err\n[forbidden-apis]   in org.apache.lucene.benchmark.quality.trec.QueryDriver (QueryDriver.java:46)\n[forbidden-apis] Forbidden field access: java.lang.System#err\n[forbidden-apis]   in org.apache.lucene.benchmark.quality.trec.QueryDriver (QueryDriver.java:47)\n[forbidden-apis] Forbidden field access: java.lang.System#err\n[forbidden-apis]   in org.apache.lucene.benchmark.quality.trec.QueryDriver (QueryDriver.java:48)\n[forbidden-apis] Forbidden field access: java.lang.System#err\n[forbidden-apis]   in org.apache.lucene.benchmark.quality.trec.QueryDriver (QueryDriver.java:49)\n[forbidden-apis] Forbidden field access: java.lang.System#err\n[forbidden-apis]   in org.apache.lucene.benchmark.quality.trec.QueryDriver (QueryDriver.java:50)\n[forbidden-apis] Forbidden field access: java.lang.System#out\n[forbidden-apis]   in org.apache.lucene.benchmark.quality.trec.QueryDriver (QueryDriver.java:65)\n[forbidden-apis] Forbidden field access: java.lang.System#err\n[forbidden-apis]   in org.apache.lucene.benchmark.quality.utils.QualityQueriesFinder (QualityQueriesFinder.java:54)\n[forbidden-apis] Forbidden field access: java.lang.System#out\n[forbidden-apis]   in org.apache.lucene.benchmark.quality.utils.QualityQueriesFinder (QualityQueriesFinder.java:60)\n[forbidden-apis] Forbidden field access: java.lang.System#out\n[forbidden-apis]   in org.apache.lucene.benchmark.quality.utils.QualityQueriesFinder (QualityQueriesFinder.java:112)\n[forbidden-apis] Forbidden field access: java.lang.System#out\n[forbidden-apis]   in org.apache.lucene.benchmark.utils.ExtractReuters (ExtractReuters.java:46)\n[forbidden-apis] Forbidden field access: java.lang.System#err\n[forbidden-apis]   in org.apache.lucene.benchmark.utils.ExtractReuters (ExtractReuters.java:63)\n[forbidden-apis] Forbidden field access: java.lang.System#err\n[forbidden-apis]   in org.apache.lucene.benchmark.utils.ExtractReuters (ExtractReuters.java:152)\n[forbidden-apis] Forbidden field access: java.lang.System#out\n[forbidden-apis]   in org.apache.lucene.benchmark.utils.ExtractWikipedia (ExtractWikipedia.java:50)\n[forbidden-apis] Forbidden field access: java.lang.System#out\n[forbidden-apis]   in org.apache.lucene.benchmark.utils.ExtractWikipedia (ExtractWikipedia.java:100)\n[forbidden-apis] Forbidden field access: java.lang.System#out\n[forbidden-apis]   in org.apache.lucene.benchmark.utils.ExtractWikipedia (ExtractWikipedia.java:111)\n[forbidden-apis] Forbidden field access: java.lang.System#out\n[forbidden-apis]   in org.apache.lucene.benchmark.utils.ExtractWikipedia (ExtractWikipedia.java:145)\n[forbidden-apis] Forbidden field access: java.lang.System#err\n[forbidden-apis]   in org.apache.lucene.benchmark.utils.ExtractWikipedia (ExtractWikipedia.java:155)\n[forbidden-apis] Forbidden field access: java.lang.System#err\n[forbidden-apis]   in org.apache.lucene.benchmark.utils.ExtractWikipedia (ExtractWikipedia.java:157)\n[forbidden-apis] Forbidden field access: java.lang.System#out\n[forbidden-apis]   in org.apache.lucene.codecs.BlockTreeTermsReader$FieldReader$SegmentTermsEnum (BlockTreeTermsReader.java:1963)\n[forbidden-apis] Forbidden field access: java.lang.System#out\n[forbidden-apis]   in org.apache.lucene.codecs.BlockTreeTermsReader$FieldReader$SegmentTermsEnum (BlockTreeTermsReader.java:1965)\n[forbidden-apis] Forbidden field access: java.lang.System#out\n[forbidden-apis]   in org.apache.lucene.codecs.BlockTreeTermsReader$FieldReader$SegmentTermsEnum (BlockTreeTermsReader.java:1973)\n[forbidden-apis] Forbidden field access: java.lang.System#out\n[forbidden-apis]   in org.apache.lucene.codecs.BlockTreeTermsReader$FieldReader$SegmentTermsEnum (BlockTreeTermsReader.java:1975)\n[forbidden-apis] Forbidden field access: java.lang.System#out\n[forbidden-apis]   in org.apache.lucene.codecs.BlockTreeTermsReader$FieldReader$SegmentTermsEnum (BlockTreeTermsReader.java:1980)\n[forbidden-apis] Forbidden field access: java.lang.System#out\n[forbidden-apis]   in org.apache.lucene.codecs.BlockTreeTermsReader$FieldReader$SegmentTermsEnum (BlockTreeTermsReader.java:1985)\n[forbidden-apis] Forbidden field access: java.lang.System#out\n[forbidden-apis]   in org.apache.lucene.codecs.BlockTreeTermsReader$FieldReader$SegmentTermsEnum (BlockTreeTermsReader.java:1992)\n[forbidden-apis] Forbidden field access: java.lang.System#out\n[forbidden-apis]   in org.apache.lucene.codecs.pulsing.PulsingPostingsWriter (PulsingPostingsWriter.java:116)\n[forbidden-apis] Forbidden field access: java.lang.System#out\n[forbidden-apis]   in org.apache.lucene.codecs.pulsing.PulsingPostingsWriter (PulsingPostingsWriter.java:128)\n[forbidden-apis] Forbidden field access: java.lang.System#out\n[forbidden-apis]   in org.apache.lucene.codecs.pulsing.PulsingPostingsWriter (PulsingPostingsWriter.java:150)\n[forbidden-apis] Forbidden field access: java.lang.System#out\n[forbidden-apis]   in org.apache.lucene.codecs.pulsing.PulsingPostingsWriter (PulsingPostingsWriter.java:154)\n[forbidden-apis] Forbidden field access: java.lang.System#out\n[forbidden-apis]   in org.apache.lucene.codecs.pulsing.PulsingPostingsWriter (PulsingPostingsWriter.java:180)\n[forbidden-apis] Forbidden field access: java.lang.System#out\n[forbidden-apis]   in org.apache.lucene.codecs.pulsing.PulsingPostingsWriter (PulsingPostingsWriter.java:210)\n[forbidden-apis] Forbidden field access: java.lang.System#out\n[forbidden-apis]   in org.apache.lucene.codecs.pulsing.PulsingPostingsWriter (PulsingPostingsWriter.java:223)\n[forbidden-apis] Forbidden field access: java.lang.System#out\n[forbidden-apis]   in org.apache.lucene.codecs.pulsing.PulsingPostingsWriter (PulsingPostingsWriter.java:255)\n[forbidden-apis] Forbidden field access: java.lang.System#out\n[forbidden-apis]   in org.apache.lucene.codecs.pulsing.PulsingPostingsWriter (PulsingPostingsWriter.java:271)\n[forbidden-apis] Forbidden field access: java.lang.System#out\n[forbidden-apis]   in org.apache.lucene.codecs.pulsing.PulsingPostingsWriter (PulsingPostingsWriter.java:344)\n[forbidden-apis] Forbidden field access: java.lang.System#out\n[forbidden-apis]   in org.apache.lucene.codecs.pulsing.PulsingPostingsWriter (PulsingPostingsWriter.java:378)\n[forbidden-apis] Forbidden field access: java.lang.System#out\n[forbidden-apis]   in org.apache.lucene.codecs.pulsing.PulsingPostingsWriter (PulsingPostingsWriter.java:387)\n[forbidden-apis] Forbidden field access: java.lang.System#out\n[forbidden-apis]   in org.apache.lucene.codecs.pulsing.PulsingPostingsWriter (PulsingPostingsWriter.java:398)\n[forbidden-apis] Forbidden field access: java.lang.System#out\n[forbidden-apis]   in org.apache.lucene.codecs.pulsing.PulsingPostingsWriter (PulsingPostingsWriter.java:402)\n[forbidden-apis] Forbidden field access: java.lang.System#out\n[forbidden-apis]   in org.apache.lucene.codecs.pulsing.PulsingPostingsWriter (PulsingPostingsWriter.java:405)\n[forbidden-apis] Forbidden field access: java.lang.System#out\n[forbidden-apis]   in org.apache.lucene.codecs.pulsing.PulsingPostingsWriter (PulsingPostingsWriter.java:408)\n[forbidden-apis] Forbidden method invocation: java.lang.Throwable#printStackTrace(java.io.PrintStream)\n[forbidden-apis]   in org.apache.lucene.index.CheckIndex (CheckIndex.java:354)\n[forbidden-apis] Forbidden method invocation: java.lang.Throwable#printStackTrace(java.io.PrintStream)\n[forbidden-apis]   in org.apache.lucene.index.CheckIndex (CheckIndex.java:388)\n[forbidden-apis] Forbidden method invocation: java.lang.Throwable#printStackTrace(java.io.PrintStream)\n[forbidden-apis]   in org.apache.lucene.index.CheckIndex (CheckIndex.java:398)\n[forbidden-apis] Forbidden method invocation: java.lang.Throwable#printStackTrace(java.io.PrintStream)\n[forbidden-apis]   in org.apache.lucene.index.CheckIndex (CheckIndex.java:600)\n[forbidden-apis] Forbidden method invocation: java.lang.Throwable#printStackTrace(java.io.PrintStream)\n[forbidden-apis]   in org.apache.lucene.index.CheckIndex (CheckIndex.java:660)\n[forbidden-apis] Forbidden method invocation: java.lang.Throwable#printStackTrace(java.io.PrintStream)\n[forbidden-apis]   in org.apache.lucene.index.CheckIndex (CheckIndex.java:1208)\n[forbidden-apis] Forbidden method invocation: java.lang.Throwable#printStackTrace(java.io.PrintStream)\n[forbidden-apis]   in org.apache.lucene.index.CheckIndex (CheckIndex.java:1249)\n[forbidden-apis] Forbidden method invocation: java.lang.Throwable#printStackTrace(java.io.PrintStream)\n[forbidden-apis]   in org.apache.lucene.index.CheckIndex (CheckIndex.java:1368)\n[forbidden-apis] Forbidden method invocation: java.lang.Throwable#printStackTrace(java.io.PrintStream)\n[forbidden-apis]   in org.apache.lucene.index.CheckIndex (CheckIndex.java:1602)\n[forbidden-apis] Forbidden field access: java.lang.System#out\n[forbidden-apis]   in org.apache.lucene.index.CheckIndex (CheckIndex.java:1691)\n[forbidden-apis] Forbidden field access: java.lang.System#out\n[forbidden-apis]   in org.apache.lucene.index.CheckIndex (CheckIndex.java:1700)\n[forbidden-apis] Forbidden field access: java.lang.System#out\n[forbidden-apis]   in org.apache.lucene.index.CheckIndex (CheckIndex.java:1707)\n[forbidden-apis] Forbidden field access: java.lang.System#out\n[forbidden-apis]   in org.apache.lucene.index.CheckIndex (CheckIndex.java:1714)\n[forbidden-apis] Forbidden field access: java.lang.System#out\n[forbidden-apis]   in org.apache.lucene.index.CheckIndex (CheckIndex.java:1723)\n[forbidden-apis] Forbidden field access: java.lang.System#out\n[forbidden-apis]   in org.apache.lucene.index.CheckIndex (CheckIndex.java:1724)\n[forbidden-apis] Forbidden field access: java.lang.System#out\n[forbidden-apis]   in org.apache.lucene.index.CheckIndex (CheckIndex.java:1753)\n[forbidden-apis] Forbidden field access: java.lang.System#out\n[forbidden-apis]   in org.apache.lucene.index.CheckIndex (CheckIndex.java:1758)\n[forbidden-apis] Forbidden field access: java.lang.System#out\n[forbidden-apis]   in org.apache.lucene.index.CheckIndex (CheckIndex.java:1762)\n[forbidden-apis] Forbidden field access: java.lang.System#out\n[forbidden-apis]   in org.apache.lucene.index.CheckIndex (CheckIndex.java:1771)\n[forbidden-apis] Forbidden field access: java.lang.System#out\n[forbidden-apis]   in org.apache.lucene.index.CheckIndex (CheckIndex.java:1772)\n[forbidden-apis] Forbidden method invocation: java.lang.Throwable#printStackTrace(java.io.PrintStream)\n[forbidden-apis]   in org.apache.lucene.index.CheckIndex (CheckIndex.java:1772)\n[forbidden-apis] Forbidden field access: java.lang.System#out\n[forbidden-apis]   in org.apache.lucene.index.CheckIndex (CheckIndex.java:1778)\n[forbidden-apis] Forbidden field access: java.lang.System#out\n[forbidden-apis]   in org.apache.lucene.index.CheckIndex (CheckIndex.java:1787)\n[forbidden-apis] Forbidden field access: java.lang.System#out\n[forbidden-apis]   in org.apache.lucene.index.CheckIndex (CheckIndex.java:1789)\n[forbidden-apis] Forbidden field access: java.lang.System#out\n[forbidden-apis]   in org.apache.lucene.index.CheckIndex (CheckIndex.java:1790)\n[forbidden-apis] Forbidden field access: java.lang.System#out\n[forbidden-apis]   in org.apache.lucene.index.CheckIndex (CheckIndex.java:1793)\n[forbidden-apis] Forbidden field access: java.lang.System#out\n[forbidden-apis]   in org.apache.lucene.index.CheckIndex (CheckIndex.java:1795)\n[forbidden-apis] Forbidden field access: java.lang.System#out\n[forbidden-apis]   in org.apache.lucene.index.CheckIndex (CheckIndex.java:1797)\n[forbidden-apis] Forbidden field access: java.lang.System#out\n[forbidden-apis]   in org.apache.lucene.index.CheckIndex (CheckIndex.java:1798)\n[forbidden-apis] Forbidden field access: java.lang.System#out\n[forbidden-apis]   in org.apache.lucene.index.CheckIndex (CheckIndex.java:1801)\n[forbidden-apis] Forbidden field access: java.lang.System#err\n[forbidden-apis]   in org.apache.lucene.index.IndexUpgrader (IndexUpgrader.java:56)\n[forbidden-apis] Forbidden field access: java.lang.System#err\n[forbidden-apis]   in org.apache.lucene.index.IndexUpgrader (IndexUpgrader.java:57)\n[forbidden-apis] Forbidden field access: java.lang.System#err\n[forbidden-apis]   in org.apache.lucene.index.IndexUpgrader (IndexUpgrader.java:58)\n[forbidden-apis] Forbidden field access: java.lang.System#err\n[forbidden-apis]   in org.apache.lucene.index.IndexUpgrader (IndexUpgrader.java:59)\n[forbidden-apis] Forbidden field access: java.lang.System#err\n[forbidden-apis]   in org.apache.lucene.index.IndexUpgrader (IndexUpgrader.java:60)\n[forbidden-apis] Forbidden field access: java.lang.System#err\n[forbidden-apis]   in org.apache.lucene.index.IndexUpgrader (IndexUpgrader.java:61)\n[forbidden-apis] Forbidden field access: java.lang.System#err\n[forbidden-apis]   in org.apache.lucene.index.IndexUpgrader (IndexUpgrader.java:62)\n[forbidden-apis] Forbidden field access: java.lang.System#err\n[forbidden-apis]   in org.apache.lucene.index.IndexUpgrader (IndexUpgrader.java:63)\n[forbidden-apis] Forbidden field access: java.lang.System#err\n[forbidden-apis]   in org.apache.lucene.index.IndexUpgrader (IndexUpgrader.java:66)\n[forbidden-apis] Forbidden field access: java.lang.System#out\n[forbidden-apis]   in org.apache.lucene.index.IndexUpgrader (IndexUpgrader.java:82)\n[forbidden-apis] Forbidden field access: java.lang.System#out\n[forbidden-apis]   in org.apache.lucene.index.IndexUpgrader (IndexUpgrader.java:87)\n[forbidden-apis] Forbidden method invocation: java.lang.Throwable#printStackTrace(java.io.PrintStream)\n[forbidden-apis]   in org.apache.lucene.search.FieldCacheImpl$Cache (FieldCacheImpl.java:279)\n[forbidden-apis] Forbidden field access: java.lang.System#out\n[forbidden-apis]   in org.apache.lucene.store.LockStressTest (LockStressTest.java:37)\n[forbidden-apis] Forbidden field access: java.lang.System#out\n[forbidden-apis]   in org.apache.lucene.store.LockStressTest (LockStressTest.java:58)\n[forbidden-apis] Forbidden field access: java.lang.System#out\n[forbidden-apis]   in org.apache.lucene.store.LockStressTest (LockStressTest.java:100)\n[forbidden-apis] Forbidden field access: java.lang.System#out\n[forbidden-apis]   in org.apache.lucene.store.LockStressTest (LockStressTest.java:104)\n[forbidden-apis] Forbidden field access: java.lang.System#out\n[forbidden-apis]   in org.apache.lucene.store.LockVerifyServer (LockVerifyServer.java:45)\n[forbidden-apis] Forbidden field access: java.lang.System#out\n[forbidden-apis]   in org.apache.lucene.store.LockVerifyServer (LockVerifyServer.java:53)\n[forbidden-apis] Forbidden field access: java.lang.System#out\n[forbidden-apis]   in org.apache.lucene.store.LockVerifyServer (LockVerifyServer.java:72)\n[forbidden-apis] Forbidden field access: java.lang.System#out\n[forbidden-apis]   in org.apache.lucene.store.LockVerifyServer (LockVerifyServer.java:78)\n[forbidden-apis] Forbidden field access: java.lang.System#out\n[forbidden-apis]   in org.apache.lucene.store.LockVerifyServer (LockVerifyServer.java:84)\n[forbidden-apis] Forbidden field access: java.lang.System#out\n[forbidden-apis]   in org.apache.lucene.util.PrintStreamInfoStream (PrintStreamInfoStream.java:65)\n[forbidden-apis] Forbidden field access: java.lang.System#err\n[forbidden-apis]   in org.apache.lucene.util.PrintStreamInfoStream (PrintStreamInfoStream.java:65)\n[forbidden-apis] Forbidden field access: java.lang.System#err\n[forbidden-apis]   in org.apache.lucene.demo.IndexFiles (IndexFiles.java:74)\n[forbidden-apis] Forbidden field access: java.lang.System#out\n[forbidden-apis]   in org.apache.lucene.demo.IndexFiles (IndexFiles.java:80)\n[forbidden-apis] Forbidden field access: java.lang.System#out\n[forbidden-apis]   in org.apache.lucene.demo.IndexFiles (IndexFiles.java:86)\n[forbidden-apis] Forbidden field access: java.lang.System#out\n[forbidden-apis]   in org.apache.lucene.demo.IndexFiles (IndexFiles.java:122)\n[forbidden-apis] Forbidden field access: java.lang.System#out\n[forbidden-apis]   in org.apache.lucene.demo.IndexFiles (IndexFiles.java:125)\n[forbidden-apis] Forbidden field access: java.lang.System#out\n[forbidden-apis]   in org.apache.lucene.demo.IndexFiles (IndexFiles.java:197)\n[forbidden-apis] Forbidden field access: java.lang.System#out\n[forbidden-apis]   in org.apache.lucene.demo.IndexFiles (IndexFiles.java:203)\n[forbidden-apis] Forbidden field access: java.lang.System#out\n[forbidden-apis]   in org.apache.lucene.demo.SearchFiles (SearchFiles.java:50)\n[forbidden-apis] Forbidden field access: java.lang.System#err\n[forbidden-apis]   in org.apache.lucene.demo.SearchFiles (SearchFiles.java:83)\n[forbidden-apis] Forbidden field access: java.lang.System#out\n[forbidden-apis]   in org.apache.lucene.demo.SearchFiles (SearchFiles.java:103)\n[forbidden-apis] Forbidden field access: java.lang.System#out\n[forbidden-apis]   in org.apache.lucene.demo.SearchFiles (SearchFiles.java:118)\n[forbidden-apis] Forbidden field access: java.lang.System#out\n[forbidden-apis]   in org.apache.lucene.demo.SearchFiles (SearchFiles.java:126)\n[forbidden-apis] Forbidden field access: java.lang.System#out\n[forbidden-apis]   in org.apache.lucene.demo.SearchFiles (SearchFiles.java:156)\n[forbidden-apis] Forbidden field access: java.lang.System#out\n[forbidden-apis]   in org.apache.lucene.demo.SearchFiles (SearchFiles.java:163)\n[forbidden-apis] Forbidden field access: java.lang.System#out\n[forbidden-apis]   in org.apache.lucene.demo.SearchFiles (SearchFiles.java:164)\n[forbidden-apis] Forbidden field access: java.lang.System#out\n[forbidden-apis]   in org.apache.lucene.demo.SearchFiles (SearchFiles.java:177)\n[forbidden-apis] Forbidden field access: java.lang.System#out\n[forbidden-apis]   in org.apache.lucene.demo.SearchFiles (SearchFiles.java:184)\n[forbidden-apis] Forbidden field access: java.lang.System#out\n[forbidden-apis]   in org.apache.lucene.demo.SearchFiles (SearchFiles.java:187)\n[forbidden-apis] Forbidden field access: java.lang.System#out\n[forbidden-apis]   in org.apache.lucene.demo.SearchFiles (SearchFiles.java:190)\n[forbidden-apis] Forbidden field access: java.lang.System#out\n[forbidden-apis]   in org.apache.lucene.demo.SearchFiles (SearchFiles.java:202)\n[forbidden-apis] Forbidden field access: java.lang.System#out\n[forbidden-apis]   in org.apache.lucene.demo.SearchFiles (SearchFiles.java:204)\n[forbidden-apis] Forbidden field access: java.lang.System#out\n[forbidden-apis]   in org.apache.lucene.demo.SearchFiles (SearchFiles.java:207)\n[forbidden-apis] Forbidden field access: java.lang.System#out\n[forbidden-apis]   in org.apache.lucene.demo.SearchFiles (SearchFiles.java:209)\n[forbidden-apis] Forbidden field access: java.lang.System#out\n[forbidden-apis]   in org.apache.lucene.demo.SearchFiles (SearchFiles.java:230)\n[forbidden-apis] Forbidden field access: java.lang.System#out\n[forbidden-apis]   in org.apache.lucene.util.collections.ArrayHashMap (ArrayHashMap.java:394)\n[forbidden-apis] Forbidden field access: java.lang.System#out\n[forbidden-apis]   in org.apache.lucene.util.collections.FloatToObjectMap (FloatToObjectMap.java:467)\n[forbidden-apis] Forbidden field access: java.lang.System#out\n[forbidden-apis]   in org.apache.lucene.util.collections.IntHashSet (IntHashSet.java:395)\n[forbidden-apis] Forbidden field access: java.lang.System#out\n[forbidden-apis]   in org.apache.lucene.util.collections.IntToDoubleMap (IntToDoubleMap.java:466)\n[forbidden-apis] Forbidden field access: java.lang.System#out\n[forbidden-apis]   in org.apache.lucene.util.collections.IntToIntMap (IntToIntMap.java:463)\n[forbidden-apis] Forbidden field access: java.lang.System#out\n[forbidden-apis]   in org.apache.lucene.util.collections.IntToObjectMap (IntToObjectMap.java:467)\n[forbidden-apis] Forbidden field access: java.lang.System#out\n[forbidden-apis]   in org.apache.lucene.util.collections.ObjectToFloatMap (ObjectToFloatMap.java:468)\n[forbidden-apis] Forbidden field access: java.lang.System#out\n[forbidden-apis]   in org.apache.lucene.util.collections.ObjectToIntMap (ObjectToIntMap.java:467)\n[forbidden-apis] Forbidden field access: java.lang.System#out\n[forbidden-apis]   in org.apache.lucene.index.CompoundFileExtractor (CompoundFileExtractor.java:57)\n[forbidden-apis] Forbidden field access: java.lang.System#out\n[forbidden-apis]   in org.apache.lucene.index.CompoundFileExtractor (CompoundFileExtractor.java:69)\n[forbidden-apis] Forbidden field access: java.lang.System#out\n[forbidden-apis]   in org.apache.lucene.index.CompoundFileExtractor (CompoundFileExtractor.java:96)\n[forbidden-apis] Forbidden field access: java.lang.System#out\n[forbidden-apis]   in org.apache.lucene.index.CompoundFileExtractor (CompoundFileExtractor.java:115)\n[forbidden-apis] Forbidden field access: java.lang.System#err\n[forbidden-apis]   in org.apache.lucene.index.IndexSplitter (IndexSplitter.java:63)\n[forbidden-apis] Forbidden field access: java.lang.System#err\n[forbidden-apis]   in org.apache.lucene.index.IndexSplitter (IndexSplitter.java:65)\n[forbidden-apis] Forbidden field access: java.lang.System#err\n[forbidden-apis]   in org.apache.lucene.index.IndexSplitter (IndexSplitter.java:66)\n[forbidden-apis] Forbidden field access: java.lang.System#out\n[forbidden-apis]   in org.apache.lucene.index.IndexSplitter (IndexSplitter.java:106)\n[forbidden-apis] Forbidden field access: java.lang.System#err\n[forbidden-apis]   in org.apache.lucene.index.MultiPassIndexSplitter (MultiPassIndexSplitter.java:102)\n[forbidden-apis] Forbidden field access: java.lang.System#err\n[forbidden-apis]   in org.apache.lucene.index.MultiPassIndexSplitter (MultiPassIndexSplitter.java:108)\n[forbidden-apis] Forbidden field access: java.lang.System#err\n[forbidden-apis]   in org.apache.lucene.index.MultiPassIndexSplitter (MultiPassIndexSplitter.java:114)\n[forbidden-apis] Forbidden field access: java.lang.System#err\n[forbidden-apis]   in org.apache.lucene.index.MultiPassIndexSplitter (MultiPassIndexSplitter.java:115)\n[forbidden-apis] Forbidden field access: java.lang.System#err\n[forbidden-apis]   in org.apache.lucene.index.MultiPassIndexSplitter (MultiPassIndexSplitter.java:116)\n[forbidden-apis] Forbidden field access: java.lang.System#err\n[forbidden-apis]   in org.apache.lucene.index.MultiPassIndexSplitter (MultiPassIndexSplitter.java:117)\n[forbidden-apis] Forbidden field access: java.lang.System#err\n[forbidden-apis]   in org.apache.lucene.index.MultiPassIndexSplitter (MultiPassIndexSplitter.java:118)\n[forbidden-apis] Forbidden field access: java.lang.System#err\n[forbidden-apis]   in org.apache.lucene.index.MultiPassIndexSplitter (MultiPassIndexSplitter.java:135)\n[forbidden-apis] Forbidden field access: java.lang.System#err\n[forbidden-apis]   in org.apache.lucene.index.MultiPassIndexSplitter (MultiPassIndexSplitter.java:141)\n[forbidden-apis] Forbidden field access: java.lang.System#err\n[forbidden-apis]   in org.apache.lucene.index.MultiPassIndexSplitter (MultiPassIndexSplitter.java:145)\n[forbidden-apis] Forbidden field access: java.lang.System#out\n[forbidden-apis]   in org.apache.lucene.misc.GetTermInfo (GetTermInfo.java:53)\n[forbidden-apis] Forbidden field access: java.lang.System#out\n[forbidden-apis]   in org.apache.lucene.misc.GetTermInfo (GetTermInfo.java:58)\n[forbidden-apis] Forbidden field access: java.lang.System#out\n[forbidden-apis]   in org.apache.lucene.misc.HighFreqTerms (HighFreqTerms.java:88)\n[forbidden-apis] Forbidden field access: java.lang.System#out\n[forbidden-apis]   in org.apache.lucene.misc.HighFreqTerms (HighFreqTerms.java:95)\n[forbidden-apis] Forbidden field access: java.lang.System#out\n[forbidden-apis]   in org.apache.lucene.misc.HighFreqTerms (HighFreqTerms.java:104)\n[forbidden-apis] Forbidden field access: java.lang.System#err\n[forbidden-apis]   in org.apache.lucene.misc.IndexMergeTool (IndexMergeTool.java:36)\n[forbidden-apis] Forbidden field access: java.lang.System#out\n[forbidden-apis]   in org.apache.lucene.misc.IndexMergeTool (IndexMergeTool.java:50)\n[forbidden-apis] Forbidden field access: java.lang.System#out\n[forbidden-apis]   in org.apache.lucene.misc.IndexMergeTool (IndexMergeTool.java:53)\n[forbidden-apis] Forbidden field access: java.lang.System#out\n[forbidden-apis]   in org.apache.lucene.misc.IndexMergeTool (IndexMergeTool.java:56)\n[forbidden-apis] Forbidden field access: java.lang.System#out\n[forbidden-apis]   in org.apache.lucene.queryparser.classic.QueryParserTokenManager (QueryParserTokenManager.java:20)\n[forbidden-apis] Forbidden field access: java.lang.System#err\n[forbidden-apis]   in org.apache.lucene.queryparser.flexible.messages.NLS (NLS.java:178)\n[forbidden-apis] Forbidden field access: java.lang.System#err\n[forbidden-apis]   in org.apache.lucene.queryparser.flexible.messages.NLS (NLS.java:182)\n[forbidden-apis] Forbidden field access: java.lang.System#out\n[forbidden-apis]   in org.apache.lucene.queryparser.flexible.standard.parser.StandardSyntaxParserTokenManager (StandardSyntaxParserTokenManager.java:46)\n[forbidden-apis] Forbidden field access: java.lang.System#out\n[forbidden-apis]   in org.apache.lucene.queryparser.surround.parser.QueryParserTokenManager (QueryParserTokenManager.java:22)\n[forbidden-apis] Forbidden field access: java.lang.System#out\n[forbidden-apis]   in org.apache.lucene.queryparser.surround.query.FieldsQuery (FieldsQuery.java:63)\n[forbidden-apis] Forbidden field access: java.lang.System#out\n[forbidden-apis]   in org.apache.lucene.spatial.prefix.tree.QuadPrefixTree (QuadPrefixTree.java:117)\n[forbidden-apis] Scanned 3081 class file(s) for forbidden API invocations (in 0.33s), 279 error(s).\n\nBUILD FAILED\n/home/rmuir/workspace/lucene-trunk/lucene/build.xml:190: Check for forbidden API calls failed, see log.\n\n ",
            "author": "Robert Muir",
            "id": "comment-13410279"
        },
        {
            "date": "2012-07-11T15:33:50+0000",
            "content": "Here's a patch: including fixes.\n\nI think its ready to commit ",
            "author": "Robert Muir",
            "id": "comment-13411634"
        },
        {
            "date": "2012-07-11T15:38:33+0000",
            "content": "+1, thanks Robert! ",
            "author": "Michael McCandless",
            "id": "comment-13411638"
        }
    ]
}