{
    "id": "LUCENE-6738",
    "title": "remove IndexWriterConfig.[gs]etIndexingChain",
    "details": {
        "resolution": "Fixed",
        "affect_versions": "None",
        "components": [],
        "labels": "",
        "fix_versions": [
            "5.4",
            "6.0"
        ],
        "priority": "Minor",
        "status": "Closed",
        "type": "Task"
    },
    "description": "github pull request with proposed code change to follow. see also LUCENE-6571 (which concerns Javadoc errors/warnings) for context.",
    "attachments": {},
    "issue_links": {},
    "comments": [
        {
            "id": "comment-14697231",
            "author": "ASF GitHub Bot",
            "date": "2015-08-14T15:31:12+0000",
            "content": "GitHub user cpoerschke opened a pull request:\n\n    https://github.com/apache/lucene-solr/pull/199\n\n    LUCENE-6738: remove IndexWriterConfig.[gs]etIndexingChain\n\n    for https://issues.apache.org/jira/i#browse/LUCENE-6738\n\nYou can merge this pull request into a Git repository by running:\n\n    $ git pull https://github.com/bloomberg/lucene-solr trunk-remove-set-indexing-chain\n\nAlternatively you can review and apply these changes as the patch at:\n\n    https://github.com/apache/lucene-solr/pull/199.patch\n\nTo close this pull request, make a commit to your master/trunk branch\nwith (at least) the following in the commit message:\n\n    This closes #199\n\n\ncommit 0acd565211055f5457477aec3e0509372b630b9b\nAuthor: Christine Poerschke <cpoerschke@bloomberg.net>\nDate:   2015-08-10T18:51:41Z\n\n    LUCENE-????: remove IndexWriterConfig.[gs]etIndexingChain\n\n "
        },
        {
            "id": "comment-14697412",
            "author": "Michael McCandless",
            "date": "2015-08-14T17:17:13+0000",
            "content": "+1 "
        },
        {
            "id": "comment-14703589",
            "author": "ASF subversion and git services",
            "date": "2015-08-19T19:11:25+0000",
            "content": "Commit 1696649 from Christine Poerschke in branch 'dev/trunk'\n[ https://svn.apache.org/r1696649 ]\n\nLUCENE-6738: remove IndexWriterConfig.[gs]etIndexingChain "
        },
        {
            "id": "comment-14703651",
            "author": "ASF subversion and git services",
            "date": "2015-08-19T19:57:44+0000",
            "content": "Commit 1696658 from Christine Poerschke in branch 'dev/branches/branch_5x'\n[ https://svn.apache.org/r1696658 ]\n\nLUCENE-6738: remove IndexWriterConfig.[gs]etIndexingChain (revision 1696649 from trunk) "
        },
        {
            "id": "comment-14703655",
            "author": "ASF GitHub Bot",
            "date": "2015-08-19T20:00:07+0000",
            "content": "Github user cpoerschke commented on the pull request:\n\n    https://github.com/apache/lucene-solr/pull/199#issuecomment-132760976\n\n    committed to trunk and merged to branch_5x "
        },
        {
            "id": "comment-14703656",
            "author": "ASF GitHub Bot",
            "date": "2015-08-19T20:00:08+0000",
            "content": "Github user cpoerschke closed the pull request at:\n\n    https://github.com/apache/lucene-solr/pull/199 "
        }
    ]
}