{
    "id": "LUCENE-447",
    "title": "Make \"ant -projecthelp\" show the javadocs and docs targets as well",
    "details": {
        "labels": "",
        "priority": "Trivial",
        "components": [
            "core/other"
        ],
        "type": "Improvement",
        "fix_versions": [
            "1.9"
        ],
        "affect_versions": "None",
        "resolution": "Fixed",
        "status": "Closed"
    },
    "description": "Added a description to the targets \"javadocs\" and \"docs\".\nThis makes ant show them when the executes \"ant -projecthelp\"",
    "attachments": {
        "build.diff": "https://issues.apache.org/jira/secure/attachment/12314759/build.diff"
    },
    "issue_links": {},
    "comments": [
        {
            "date": "2005-10-07T19:02:38+0000",
            "content": "attached diff. ",
            "author": "Luc Vanlerberghe",
            "id": "comment-12331577"
        },
        {
            "date": "2005-10-08T20:04:04+0000",
            "content": "Thanks, the patch has juts been committed. ",
            "author": "Daniel Naber",
            "id": "comment-12331644"
        }
    ]
}