{
    "id": "SOLR-3694",
    "title": "Thread leak in SolrCmdDistributor (thread pool not closed).",
    "details": {
        "labels": "",
        "priority": "Major",
        "components": [],
        "type": "Bug",
        "fix_versions": [],
        "affect_versions": "None",
        "resolution": "Unresolved",
        "status": "Open"
    },
    "description": "This thing leaks threads:\n\n  // TODO: shut this thing down\n  // TODO: this cannot be per instance...\n  static BoundedExecutor commExecutor;\n\n\n\n(unclosed internal thread pool).",
    "attachments": {},
    "issue_links": {},
    "comments": []
}