{
    "id": "LUCENE-2623",
    "title": "Random Test Failure org.apache.lucene.index.TestIndexWriter.testAddIndexesWithThreads (from TestIndexWriter)",
    "details": {
        "labels": "",
        "priority": "Minor",
        "components": [
            "general/test"
        ],
        "type": "Bug",
        "fix_versions": [],
        "affect_versions": "None",
        "resolution": "Unresolved",
        "status": "Open"
    },
    "description": "Error Message\n\nexpected:<3160> but was:<2752>\nStacktrace\n\njunit.framework.AssertionFailedError: expected:<3160> but was:<2752>\n\tat\norg.apache.lucene.index.TestIndexWriter.testAddIndexesWithThreads(TestIndexWriter.java:3794)\n\tat org.apache.lucene.util.LuceneTestCase.runBare(LuceneTestCase.java:380)\n\tat org.apache.lucene.util.LuceneTestCase.run(LuceneTestCase.java:372)\nStandard Output\n\njava.lang.AssertionError: IndexFileDeleter doesn't know about file _8h.cfs\n\tat org.apache.lucene.index.IndexWriter.filesExist(IndexWriter.java:4284)\n\tat org.apache.lucene.index.IndexWriter.startCommit(IndexWriter.java:4331)\n\tat org.apache.lucene.index.IndexWriter.prepareCommit(IndexWriter.java:3088)\n\tat org.apache.lucene.index.IndexWriter.commit(IndexWriter.java:3161)\n\tat org.apache.lucene.index.IndexWriter.commit(IndexWriter.java:3132)\n\tat\norg.apache.lucene.index.TestIndexWriter$CommitAndAddIndexes.doBody(TestIndexWriter.java:3774)\n\tat\norg.apache.lucene.index.TestIndexWriter$RunAddIndexesThreads$1.run(TestIndexWriter.java:3710)\nNOTE: random codec of testcase 'testAddIndexesWithThreads' was: MockSep\nNOTE: random locale of testcase 'testAddIndexesWithThreads' was: ms_MY\nNOTE: random timezone of testcase 'testAddIndexesWithThreads' was:\nAsia/Aqtau\nNOTE: random seed of testcase 'testAddIndexesWithThreads' was:\n-5272061551011630291",
    "attachments": {},
    "issue_links": {},
    "comments": []
}