{
    "id": "SOLR-8753",
    "title": "When a replica attempts to become leader and cannot, it should not update its last published state when it moves into RECOVERING.",
    "details": {
        "components": [],
        "type": "Improvement",
        "labels": "",
        "fix_versions": [],
        "affect_versions": "None",
        "status": "Open",
        "resolution": "Unresolved",
        "priority": "Major"
    },
    "description": "The reason it could not become leader may be temporary. Currently, whenever you give up trying to become leader, you also poison any future attempt by making the last published state not ACTIVE when getting back in line.",
    "attachments": {},
    "issue_links": {},
    "comments": []
}