{
    "id": "SOLR-299",
    "title": "Audit use of backticks in solr.py",
    "details": {
        "affect_versions": "1.2",
        "status": "Closed",
        "fix_versions": [
            "1.3"
        ],
        "components": [
            "clients - python"
        ],
        "type": "Bug",
        "priority": "Major",
        "labels": "",
        "resolution": "Fixed"
    },
    "description": "backticks are often the wrong thing to do (they return a \"debugging\" representation of a variable).\n\nThis may be superceded by the new python client, but should be fixed in the mean time.",
    "attachments": {},
    "issue_links": {},
    "comments": [
        {
            "author": "Mike Klaas",
            "id": "comment-12525173",
            "date": "2007-09-05T18:16:40+0000",
            "content": "committed r573019 "
        }
    ]
}