{
    "id": "SOLR-11419",
    "title": "Validation command for missing docs in test-patch",
    "details": {
        "labels": "",
        "priority": "Major",
        "components": [
            "Tests"
        ],
        "type": "Improvement",
        "fix_versions": [],
        "affect_versions": "None",
        "resolution": "Unresolved",
        "status": "Open"
    },
    "description": "Based on the discussion under SOLR-10912, patches should be validated if they include documentation changes.\n\nAdditionally, the tool could suggest .adoc file to be updated, based on the changed files.",
    "attachments": {},
    "issue_links": {},
    "comments": []
}