{
    "id": "SOLR-5798",
    "title": "Update to Hadoop 2.3.0",
    "details": {
        "affect_versions": "None",
        "status": "Closed",
        "fix_versions": [],
        "components": [],
        "type": "Improvement",
        "priority": "Major",
        "labels": "",
        "resolution": "Duplicate"
    },
    "description": "",
    "attachments": {},
    "issue_links": {},
    "comments": [
        {
            "author": "Uwe Schindler",
            "id": "comment-13970983",
            "date": "2014-04-16T12:56:48+0000",
            "content": "Move issue to Solr 4.9. "
        }
    ]
}