{
    "id": "SOLR-1741",
    "title": "NPE when deletionPolicy sets maxOptimizedCommitsTokeep=0",
    "details": {
        "affect_versions": "1.4",
        "status": "Closed",
        "fix_versions": [
            "4.3"
        ],
        "components": [
            "replication (java)"
        ],
        "type": "Bug",
        "priority": "Minor",
        "labels": "",
        "resolution": "Cannot Reproduce"
    },
    "description": "This is a user reported issue http://markmail.org/thread/bjcwiw3s66b5x76h",
    "attachments": {},
    "issue_links": {},
    "comments": [
        {
            "author": "Hoss Man",
            "id": "comment-12872577",
            "date": "2010-05-27T22:08:09+0000",
            "content": "Bulk updating 240 Solr issues to set the Fix Version to \"next\" per the process outlined in this email...\n\nhttp://mail-archives.apache.org/mod_mbox/lucene-dev/201005.mbox/%3Calpine.DEB.1.10.1005251052040.24672@radix.cryptio.net%3E\n\nSelection criteria was \"Unresolved\" with a Fix Version of 1.5, 1.6, 3.1, or 4.0.  email notifications were suppressed.\n\nA unique token for finding these 240 issues in the future: hossversioncleanup20100527 "
        },
        {
            "author": "Robert Muir",
            "id": "comment-13043781",
            "date": "2011-06-03T16:47:01+0000",
            "content": "Bulk move 3.2 -> 3.3 "
        },
        {
            "author": "Robert Muir",
            "id": "comment-13106297",
            "date": "2011-09-16T14:50:26+0000",
            "content": "3.4 -> 3.5 "
        },
        {
            "author": "Hoss Man",
            "id": "comment-13412070",
            "date": "2012-07-11T22:25:54+0000",
            "content": "bulk fixing the version info for 4.0-ALPHA and 4.0 all affected issues have \"hoss20120711-bulk-40-change\" in comment "
        },
        {
            "author": "Robert Muir",
            "id": "comment-13429824",
            "date": "2012-08-07T03:43:22+0000",
            "content": "rmuir20120906-bulk-40-change "
        },
        {
            "author": "Robert Muir",
            "id": "comment-13452183",
            "date": "2012-09-10T17:41:57+0000",
            "content": "moving all 4.0 issues not touched in a month to 4.1 "
        },
        {
            "author": "Uwe Schindler",
            "id": "comment-13654168",
            "date": "2013-05-10T10:34:16+0000",
            "content": "Closed after release. "
        }
    ]
}