{
    "id": "SOLR-151",
    "title": "Add support for the Optimize command",
    "details": {
        "affect_versions": "None",
        "status": "Closed",
        "fix_versions": [],
        "components": [
            "clients - ruby - flare"
        ],
        "type": "Improvement",
        "priority": "Major",
        "labels": "",
        "resolution": "Fixed"
    },
    "description": "",
    "attachments": {
        "solrb_optimize_command.diff": "https://issues.apache.org/jira/secure/attachment/12350715/solrb_optimize_command.diff"
    },
    "issue_links": {},
    "comments": [
        {
            "author": "Coda Hale",
            "id": "comment-12471525",
            "date": "2007-02-08T23:38:11+0000",
            "content": "This adds support for the Optimize command to solrb. Unit tests, functional tests.\n\n(The patch may be kind of hinky \u2013 hopefully it's smart enough to deal with me manually removing unrelated changes from the diff. If it chokes on this, I can apply these changes to a pristine working copy and re-submit.) "
        },
        {
            "author": "Erik Hatcher",
            "id": "comment-12471546",
            "date": "2007-02-09T01:10:40+0000",
            "content": "patch was a little hinkey, but i manually patched it.  all is well.  committed.  thanks Coda, you're rocking! "
        }
    ]
}