{
    "id": "SOLR-1515",
    "title": "Javadoc typo in SolrQueryResponse",
    "details": {
        "affect_versions": "1.3",
        "status": "Closed",
        "fix_versions": [
            "1.4"
        ],
        "components": [
            "search"
        ],
        "type": "Improvement",
        "priority": "Trivial",
        "labels": "",
        "resolution": "Fixed"
    },
    "description": "There is a minute typo in the javadoc for o.a.s.request.SolrQueryResponse.java. This patch fixes that.",
    "attachments": {
        "SOLR-1515.101709.Mattmann.patch.txt": "https://issues.apache.org/jira/secure/attachment/12422462/SOLR-1515.101709.Mattmann.patch.txt"
    },
    "issue_links": {},
    "comments": [
        {
            "author": "Chris A. Mattmann",
            "id": "comment-12766970",
            "date": "2009-10-17T22:00:17+0000",
            "content": "\n\tpatch with javadoc fix\n\n "
        },
        {
            "author": "Koji Sekiguchi",
            "id": "comment-12766995",
            "date": "2009-10-18T00:32:15+0000",
            "content": "Committed revision 826321. Thanks. "
        },
        {
            "author": "Grant Ingersoll",
            "id": "comment-12775912",
            "date": "2009-11-10T15:52:17+0000",
            "content": "Bulk close for Solr 1.4 "
        }
    ]
}