{
    "id": "SOLR-11354",
    "title": "Add factorial and movingMedian Stream Evaluators",
    "details": {
        "labels": "",
        "priority": "Major",
        "components": [],
        "type": "New Feature",
        "fix_versions": [
            "7.1",
            "master (8.0)"
        ],
        "affect_versions": "None",
        "resolution": "Resolved",
        "status": "Resolved"
    },
    "description": "This ticket will add the factorial and movingMedian Stream Evaluators:\n\nSyntax:\n\nfactorial(N)\n\nmovingMedian(colA)",
    "attachments": {},
    "issue_links": {},
    "comments": [
        {
            "date": "2017-09-20T01:43:07+0000",
            "content": "Commit 565b6c6e5ac349a06a15bc8cd2b011d0b89b8769 in lucene-solr's branch refs/heads/master from Joel Bernstein\n[ https://git-wip-us.apache.org/repos/asf?p=lucene-solr.git;h=565b6c6 ]\n\nSOLR-11354: Add factorial and movingMedian Stream Evaluators ",
            "author": "ASF subversion and git services",
            "id": "comment-16172594"
        },
        {
            "date": "2017-09-20T01:43:14+0000",
            "content": "Commit e0327719a3a430ccc1e7292270e78196d8a61723 in lucene-solr's branch refs/heads/master from Joel Bernstein\n[ https://git-wip-us.apache.org/repos/asf?p=lucene-solr.git;h=e032771 ]\n\nSOLR-11354: Fix precommit ",
            "author": "ASF subversion and git services",
            "id": "comment-16172595"
        },
        {
            "date": "2017-09-20T01:43:16+0000",
            "content": "Commit a2cd9c12d59855143526e11a6d26f95d2e89ba4c in lucene-solr's branch refs/heads/master from Joel Bernstein\n[ https://git-wip-us.apache.org/repos/asf?p=lucene-solr.git;h=a2cd9c1 ]\n\nSOLR-11354: Fix /stream handler ",
            "author": "ASF subversion and git services",
            "id": "comment-16172596"
        },
        {
            "date": "2017-09-20T01:51:51+0000",
            "content": "Commit ec725b94ca378dd6438d0ceef34e0c8adfa6dcde in lucene-solr's branch refs/heads/branch_7x from Joel Bernstein\n[ https://git-wip-us.apache.org/repos/asf?p=lucene-solr.git;h=ec725b9 ]\n\nSOLR-11354: Add factorial and movingMedian Stream Evaluators ",
            "author": "ASF subversion and git services",
            "id": "comment-16172602"
        },
        {
            "date": "2017-09-20T01:51:54+0000",
            "content": "Commit 376647dc617b6710bcdb117b1482dc91e5c378f4 in lucene-solr's branch refs/heads/branch_7x from Joel Bernstein\n[ https://git-wip-us.apache.org/repos/asf?p=lucene-solr.git;h=376647d ]\n\nSOLR-11354: Fix precommit ",
            "author": "ASF subversion and git services",
            "id": "comment-16172603"
        },
        {
            "date": "2017-09-20T01:51:56+0000",
            "content": "Commit f2e8134f8b5e4e38218405a147cda2356c421023 in lucene-solr's branch refs/heads/branch_7x from Joel Bernstein\n[ https://git-wip-us.apache.org/repos/asf?p=lucene-solr.git;h=f2e8134 ]\n\nSOLR-11354: Fix /stream handler ",
            "author": "ASF subversion and git services",
            "id": "comment-16172604"
        }
    ]
}