{
    "id": "SOLR-6725",
    "title": "add suggester to stock configs",
    "details": {
        "components": [],
        "type": "Improvement",
        "labels": "",
        "fix_versions": [],
        "affect_versions": "None",
        "status": "Open",
        "resolution": "Unresolved",
        "priority": "Major"
    },
    "description": "SOLR-6679 removed the suggester component/request handler from the example configs since it was not \"lazy\" (i.e. it did a lot of work and impacted performance and startup time even if it wasn't used).\n\nWe should re-add a good default suggester that has no overhead if it isn't used.",
    "attachments": {},
    "issue_links": {},
    "comments": []
}