{
    "id": "SOLR-1361",
    "title": "Incorrect javadoc on SolrInputDocument addField",
    "details": {
        "affect_versions": "1.4",
        "status": "Closed",
        "fix_versions": [
            "1.4"
        ],
        "components": [],
        "type": "Improvement",
        "priority": "Minor",
        "labels": "",
        "resolution": "Fixed"
    },
    "description": "SolrInputDocument#addField(String, Object, float) has a comment copied from #clearAll().  The comment should reflect that the method adds a field.",
    "attachments": {
        "SOLR-1361.patch": "https://issues.apache.org/jira/secure/attachment/12416446/SOLR-1361.patch"
    },
    "issue_links": {},
    "comments": [
        {
            "author": "Shalin Shekhar Mangar",
            "id": "comment-12743095",
            "date": "2009-08-14T06:30:34+0000",
            "content": "Committed revision 804088.\n\nThanks Chris! "
        },
        {
            "author": "Grant Ingersoll",
            "id": "comment-12775842",
            "date": "2009-11-10T15:52:13+0000",
            "content": "Bulk close for Solr 1.4 "
        }
    ]
}