{
    "id": "SOLR-9848",
    "title": "Lower solr.cloud.wait-for-updates-with-stale-state-pause back down from 7 seconds.",
    "details": {
        "components": [],
        "type": "Improvement",
        "labels": "",
        "fix_versions": [
            "6.5",
            "7.0"
        ],
        "affect_versions": "None",
        "status": "Closed",
        "resolution": "Fixed",
        "priority": "Major"
    },
    "description": "While looking for replica out of sync issues we jacked this up hoping it might be involved, but I don't that it was and we should look at returning to a 2 second wait or so by default.",
    "attachments": {},
    "issue_links": {},
    "comments": [
        {
            "date": "2017-02-22T15:13:52+0000",
            "author": "ASF subversion and git services",
            "content": "Commit eb9e3cba8d9d14991bfdc6451849947217fcb1e1 in lucene-solr's branch refs/heads/master from markrmiller\n[ https://git-wip-us.apache.org/repos/asf?p=lucene-solr.git;h=eb9e3cb ]\n\nSOLR-9848: Lower solr.cloud.wait-for-updates-with-stale-state-pause back down from 7 seconds. ",
            "id": "comment-15878438"
        },
        {
            "date": "2017-02-22T15:24:55+0000",
            "author": "ASF subversion and git services",
            "content": "Commit f8ddebc61410b8a6162766d7e0c913004f9ae098 in lucene-solr's branch refs/heads/branch_6x from markrmiller\n[ https://git-wip-us.apache.org/repos/asf?p=lucene-solr.git;h=f8ddebc ]\n\nSOLR-9848: Lower solr.cloud.wait-for-updates-with-stale-state-pause back down from 7 seconds. ",
            "id": "comment-15878474"
        }
    ]
}