{
    "id": "SOLR-7740",
    "title": "tweak TestConfigOverlay.testPaths - auto[Soft]Commit(./)max(Docs|Time)",
    "details": {
        "components": [],
        "type": "Test",
        "labels": "",
        "fix_versions": [
            "5.3"
        ],
        "affect_versions": "None",
        "status": "Closed",
        "resolution": "Fixed",
        "priority": "Minor"
    },
    "description": "github pull request to follow",
    "attachments": {},
    "issue_links": {},
    "comments": [
        {
            "date": "2015-06-30T20:53:45+0000",
            "author": "ASF GitHub Bot",
            "content": "GitHub user cpoerschke opened a pull request:\n\n    https://github.com/apache/lucene-solr/pull/177\n\n    SOLR-7740: tweak TestConfigOverlay.testPaths\n\n    for https://issues.apache.org/jira/i#browse/SOLR-7740\n\nYou can merge this pull request into a Git repository by running:\n\n    $ git pull https://github.com/bloomberg/lucene-solr trunk-test-config-overlay\n\nAlternatively you can review and apply these changes as the patch at:\n\n    https://github.com/apache/lucene-solr/pull/177.patch\n\nTo close this pull request, make a commit to your master/trunk branch\nwith (at least) the following in the commit message:\n\n    This closes #177\n\n\ncommit 6f18820e5394bcc4b79be92b8db4d2dde10f386b\nAuthor: Christine Poerschke <cpoerschke@bloomberg.net>\nDate:   2015-06-30T20:15:51Z\n\n    SOLR-????: tweak TestConfigOverlay.testPaths - auto[Soft]Commit(./)max(Docs|Time)\n\n    The autoCommit(./)max(Docs|Time) asserts appear twice and from quick look at ConfigOverlay the second autoCommit could have been intended to be autoSoftCommit instead.\n\n ",
            "id": "comment-14609051"
        },
        {
            "date": "2015-07-01T11:15:15+0000",
            "author": "ASF subversion and git services",
            "content": "Commit 1688619 from Ramkumar Aiyengar in branch 'dev/trunk'\n[ https://svn.apache.org/r1688619 ]\n\nSOLR-7740: Fix typo bug with TestConfigOverlay ",
            "id": "comment-14609949"
        },
        {
            "date": "2015-07-01T11:16:35+0000",
            "author": "ASF subversion and git services",
            "content": "Commit 1688621 from Ramkumar Aiyengar in branch 'dev/branches/branch_5x'\n[ https://svn.apache.org/r1688621 ]\n\nSOLR-7740: Fix typo bug with TestConfigOverlay ",
            "id": "comment-14609951"
        },
        {
            "date": "2015-07-01T11:17:31+0000",
            "author": "Ramkumar Aiyengar",
            "content": "Thanks Christine! ",
            "id": "comment-14609953"
        },
        {
            "date": "2015-08-26T13:06:27+0000",
            "author": "Shalin Shekhar Mangar",
            "content": "Bulk close for 5.3.0 release ",
            "id": "comment-14713331"
        },
        {
            "date": "2016-01-12T18:54:19+0000",
            "author": "ASF GitHub Bot",
            "content": "Github user cpoerschke closed the pull request at:\n\n    https://github.com/apache/lucene-solr/pull/177 ",
            "id": "comment-15094484"
        }
    ]
}