{
    "id": "SOLR-5155",
    "title": "solr contrib tests should also use solrconfig.snippet.randomindexconfig.xml",
    "details": {
        "affect_versions": "None",
        "status": "Open",
        "fix_versions": [],
        "components": [],
        "type": "Sub-task",
        "priority": "Major",
        "labels": "",
        "resolution": "Unresolved"
    },
    "description": "solrconfig.snippet.randomindexconfig.xml currently lives in solr/core making it easy to xinclude in all solr/core tests \u2013 it's not clear if there's a nice simple easy way to also include it in all contrib tests, but we should try to find one.",
    "attachments": {},
    "issue_links": {},
    "comments": []
}