{
    "id": "SOLR-12904",
    "title": "Log Delete Query Processor custom Solr component",
    "details": {
        "type": "Task",
        "status": "Open",
        "labels": "",
        "fix_versions": [],
        "components": [],
        "priority": "Minor",
        "resolution": "Unresolved",
        "affect_versions": "None"
    },
    "description": "Added a\u00a0Log Delete Query Processor custom Solr component (https://github.com/apache/lucene-solr/pull/483)\u00a0:\n\n\tIts mainly used to identify the delete queries and log them separately to identify the delete queries performed.\n\tIt helps to maintain track of any deletes going on in Solr.",
    "attachments": {},
    "issue_links": {},
    "comments": [
        {
            "id": "comment-16711929",
            "content": "Hi guys, it would be great if someone could review my PR.\n\n\u00a0\n\nThanks. ",
            "author": "Tirth Rajen Mehta",
            "date": "2018-12-06T19:37:25+0000"
        }
    ]
}