{
    "id": "SOLR-1310",
    "title": "Upgrade to Tika 0.4",
    "details": {
        "affect_versions": "None",
        "status": "Closed",
        "fix_versions": [
            "1.4"
        ],
        "components": [],
        "type": "Improvement",
        "priority": "Minor",
        "labels": "",
        "resolution": "Fixed"
    },
    "description": "As title says.",
    "attachments": {},
    "issue_links": {},
    "comments": [
        {
            "author": "Grant Ingersoll",
            "id": "comment-12735709",
            "date": "2009-07-27T18:49:24+0000",
            "content": "Committed revision 798253. "
        }
    ]
}