{
    "id": "SOLR-9626",
    "title": "Admin UI (new) does not include highlighting indicating match in Analysis View",
    "details": {
        "components": [
            "Admin UI"
        ],
        "type": "Bug",
        "labels": "",
        "fix_versions": [
            "6.4",
            "7.0"
        ],
        "affect_versions": "6.2",
        "status": "Closed",
        "resolution": "Fixed",
        "priority": "Minor"
    },
    "description": "When using the analysis view in the new Solr Admin UI, an index-query time match should be indicated by highlighting the final result in the chain. This works in the old UI but not the new UI.",
    "attachments": {},
    "issue_links": {},
    "comments": [
        {
            "date": "2016-11-20T11:24:00+0000",
            "author": "ASF subversion and git services",
            "content": "Commit 380b5ca626b396f1231936ca5d581416866f11b1 in lucene-solr's branch refs/heads/master from Alexandre Rafalovitch\n[ https://git-wip-us.apache.org/repos/asf?p=lucene-solr.git;h=380b5ca ]\n\nSOLR-9626: Add css class, when match key is found ",
            "id": "comment-15680997"
        },
        {
            "date": "2016-11-20T11:35:28+0000",
            "author": "ASF subversion and git services",
            "content": "Commit df6d86d5f6d8d9f0eda5f7f818c7a94a9729ddd4 in lucene-solr's branch refs/heads/branch_6x from Alexandre Rafalovitch\n[ https://git-wip-us.apache.org/repos/asf?p=lucene-solr.git;h=df6d86d ]\n\nSOLR-9626: Add css class, when match key is found ",
            "id": "comment-15681010"
        },
        {
            "date": "2016-11-20T11:37:53+0000",
            "author": "Alexandre Rafalovitch",
            "content": "This was a clear regression, so I just ported the old logic to the new code. It's been tested with techproducts example. ",
            "id": "comment-15681014"
        }
    ]
}