{
    "id": "SOLR-4689",
    "title": "Overseer should assign node names by default for the collections API split command",
    "details": {
        "affect_versions": "None",
        "status": "Open",
        "fix_versions": [],
        "components": [
            "SolrCloud"
        ],
        "type": "Improvement",
        "priority": "Major",
        "labels": "",
        "resolution": "Unresolved"
    },
    "description": "Integrate Marks` changes for delegating node name assignment to Overseer SOLR-4655 for the SPLITSHARD collections API.",
    "attachments": {},
    "issue_links": {},
    "comments": []
}