{
    "id": "SOLR-12996",
    "title": "ShingleFilterFactory fillerToken parameter is not in Reference Guide",
    "details": {
        "type": "Improvement",
        "status": "Open",
        "labels": "",
        "fix_versions": [],
        "components": [
            "documentation"
        ],
        "priority": "Minor",
        "resolution": "Unresolved",
        "affect_versions": "7.5"
    },
    "description": "An issue came up on the mailing list regarding shingle configuration. And we noticed that fillerToken parameter is in Javadocs (and source) but not in the Reference Guide.",
    "attachments": {},
    "issue_links": {},
    "comments": []
}